Workbook

Sheet Alocação em ações_anual
A1: Date | B1: Fundos ativos | C1: Fundos de investimento estrangeiro | D1: Outros | E1: Total Ações (R\$ mi)
A2: 42705 | B2: 0.52761634 | C2: 0.086138654 | D2: 0.38624501 | E2: 150274.76
A3: 43070 | B3: 0.5019665 | C3: 0.22704975 | D3: 0.27098375 | E3: 228067.13
A4: 43435 | B4: 0.47960291 | C4: 0.18021116 | D4: 0.34018593 | E4: 301741.53
A5: 43800 | B5: 0.59668185 | C5: 0.17733358 | D5: 0.22598457 | E5: 496516.89
A6: 44166 | B6: 0.62975702 | C6: 0.1706477 | D6: 0.19959528 | E6: 607293.46
A7: 44531 | B7: 0.61505016 | C7: 0.25108328 | D7: 0.13386656 | E7: 583805.98
A8: 44896 | B8: 0.53421214 | C8: 0.23112824 | D8: 0.23465962 | E8: 523586.89
A9: 45261 | B9: 0.48832293 | C9: 0.24822005 | D9: 0.26345702 | E9: 627948.41
A10: 45627 | B10: 0.44009248 | C10: 0.30595388 | D10: 0.25395364 | E10: 578025.46
A11: 45992 | B11: 0.43854371 | C11: 0.3804029 | D11: 0.18105339 | E11: 666360.28
A12: 46174 | B12: 0.42733524 | C12: 0.40454655 | D12: 0.16811821 | E12: 681503.23

Sheet AUM Allocation (Annual)
A1: Date | B1: Fixed Income as % of Total Net AUM | C1: Equities as % of Total Net AUM (RHS) | D1: Hedge Funds as % of Total Net AUM | E1: Others as % of Total Net AUM | F1: Total Net AUM | G1: Total equities AUM | H1: Total AUM of funds industry | I1: Total Net AUM (R$ tri) | J1: Total equities AUM (R$ tri) | K1: Total AUM of funds industry (R$ tri)
A2: 26634 | B2: 0 | C2: 1 | D2: 0 | E2: 0 | F2: 25676.607 | G2: 25676.607 | H2: 25676.607 | I2: =AUM_Allocation__Annual[[#This Row],[Total Net AUM]]/100000 -> 0.25676607 | J2: =AUM_Allocation__Annual[[#This Row],[Total equities AUM]]/1000000 -> 0.025676607 | K2: =AUM_Allocation__Annual[[#This Row],[Total AUM of funds industry]]/1000000 -> 0.025676607
A3: 26999 | B3: 0 | C3: 1 | D3: 0 | E3: 0 | F3: 23531.891 | G3: 23531.891 | H3: 23531.891 | I3: =AUM_Allocation__Annual[[#This Row],[Total Net AUM]]/100000 -> 0.23531891 | J3: =AUM_Allocation__Annual[[#This Row],[Total equities AUM]]/1000000 -> 0.023531891 | K3: =AUM_Allocation__Annual[[#This Row],[Total AUM of funds industry]]/1000000 -> 0.023531891
A4: 27364 | B4: 0 | C4: 1 | D4: 0 | E4: 0 | F4: 19410.742 | G4: 19410.742 | H4: 19410.742 | I4: =AUM_Allocation__Annual[[#This Row],[Total Net AUM]]/100000 -> 0.19410742 | J4: =AUM_Allocation__Annual[[#This Row],[Total equities AUM]]/1000000 -> 0.019410742 | K4: =AUM_Allocation__Annual[[#This Row],[Total AUM of funds industry]]/1000000 -> 0.019410742
A5: 27729 | B5: 0 | C5: 1 | D5: 0 | E5: 0 | F5: 21281.571 | G5: 21281.571 | H5: 21281.571 | I5: =AUM_Allocation__Annual[[#This Row],[Total Net AUM]]/100000 -> 0.21281571 | J5: =AUM_Allocation__Annual[[#This Row],[Total equities AUM]]/1000000 -> 0.021281571 | K5: =AUM_Allocation__Annual[[#This Row],[Total AUM of funds industry]]/1000000 -> 0.021281571
A6: 28095 | B6: 0 | C6: 1 | D6: 0 | E6: 0 | F6: 22886.17 | G6: 22886.17 | H6: 22886.17 | I6: =AUM_Allocation__Annual[[#This Row],[Total Net AUM]]/100000 -> 0.2288617 | J6: =AUM_Allocation__Annual[[#This Row],[Total equities AUM]]/1000000 -> 0.02288617 | K6: =AUM_Allocation__Annual[[#This Row],[Total AUM of funds industry]]/1000000 -> 0.02288617
A7: 28460 | B7: 0 | C7: 1 | D7: 0 | E7: 0 | F7: 28617.825 | G7: 28617.825 | H7: 28617.825 | I7: =AUM_Allocation__Annual[[#This Row],[Total Net AUM]]/100000 -> 0.28617825 | J7: =AUM_Allocation__Annual[[#This Row],[Total equities AUM]]/1000000 -> 0.028617825 | K7: =AUM_Allocation__Annual[[#This Row],[Total AUM of funds industry]]/1000000 -> 0.028617825
A8: 28825 | B8: 0 | C8: 1 | D8: 0 | E8: 0 | F8: 27537.295 | G8: 27537.295 | H8: 27537.295 | I8: =AUM_Allocation__Annual[[#This Row],[Total Net AUM]]/100000 -> 0.27537295 | J8: =AUM_Allocation__Annual[[#This Row],[Total equities AUM]]/1000000 -> 0.027537295 | K8: =AUM_Allocation__Annual[[#This Row],[Total AUM of funds industry]]/1000000 -> 0.027537295
A9: 29190 | B9: 0 | C9: 1 | D9: 0 | E9: 0 | F9: 30236.435 | G9: 30236.435 | H9: 30236.435 | I9: =AUM_Allocation__Annual[[#This Row],[Total Net AUM]]/100000 -> 0.30236435 | J9: =AUM_Allocation__Annual[[#This Row],[Total equities AUM]]/1000000 -> 0.030236435 | K9: =AUM_Allocation__Annual[[#This Row],[Total AUM of funds industry]]/1000000 -> 0.030236435
A10: 29556 | B10: 0 | C10: 1 | D10: 0 | E10: 0 | F10: 21612.003 | G10: 21612.003 | H10: 21612.003 | I10: =AUM_Allocation__Annual[[#This Row],[Total Net AUM]]/100000 -> 0.21612003 | J10: =AUM_Allocation__Annual[[#This Row],[Total equities AUM]]/1000000 -> 0.021612003 | K10: =AUM_Allocation__Annual[[#This Row],[Total AUM of funds industry]]/1000000 -> 0.021612003
A11: 29921 | B11: 0 | C11: 1 | D11: 0 | E11: 0 | F11: 21989.128 | G11: 21989.128 | H11: 21989.128 | I11: =AUM_Allocation__Annual[[#This Row],[Total Net AUM]]/100000 -> 0.21989128 | J11: =AUM_Allocation__Annual[[#This Row],[Total equities AUM]]/1000000 -> 0.021989128 | K11: =AUM_Allocation__Annual[[#This Row],[Total AUM of funds industry]]/1000000 -> 0.021989128
A12: 30286 | B12: 0 | C12: 1 | D12: 0 | E12: 0 | F12: 24148.401 | G12: 24148.401 | H12: 24148.401 | I12: =AUM_Allocation__Annual[[#This Row],[Total Net AUM]]/100000 -> 0.24148401 | J12: =AUM_Allocation__Annual[[#This Row],[Total equities AUM]]/1000000 -> 0.024148401 | K12: =AUM_Allocation__Annual[[#This Row],[Total AUM of funds industry]]/1000000 -> 0.024148401
A13: 30651 | B13: 0 | C13: 1 | D13: 0 | E13: 0 | F13: 37953.41 | G13: 37953.41 | H13: 37953.41 | I13: =AUM_Allocation__Annual[[#This Row],[Total Net AUM]]/100000 -> 0.3795341 | J13: =AUM_Allocation__Annual[[#This Row],[Total equities AUM]]/1000000 -> 0.03795341 | K13: =AUM_Allocation__Annual[[#This Row],[Total AUM of funds industry]]/1000000 -> 0.03795341
... A56: 46174 | B56: 0.42773782 | C56: 0.061469015 | D56: 0.13933647 | E56: 0.37145669 | F56: 6968621.4 | G56: 681503.23 | H56: 11086939 | I56: =AUM_Allocation__Annual[[#This Row],[Total Net AUM]]/100000 -> 69.686214 | J56: =AUM_Allocation__Annual[[#This Row],[Total equities AUM]]/1000000 -> 0.68150323 | K56: =AUM_Allocation__Annual[[#This Row],[Total AUM of funds industry]]/1000000 -> 11.086939

Sheet Cap  Líq  Ações Grupo (12M)
A1: Data | B1: Ações (total) | C1: Fundos ativos | D1: Fundos de investimento estrangeiro | E1: Outros | F1: Ações (total) (R$ billion) | G1: Fundos ativos (R$ billion) | H1: Fundos de investimento estrangeiro (R$ billion) | I1: Outros (R$ billion)
A2: 45839 | B2: -5157.0561 | C2: -5379.6571 | D2: 937.10661 | E2: -714.50564 | F2: =Cap__Líq__Ações_Grupo__12M___2[[#This Row],[Ações (total)]]/1000 -> -5.1570561 | G2: =Cap__Líq__Ações_Grupo__12M___2[[#This Row],[Fundos ativos]]/1000 -> -5.3796571 | H2: =Cap__Líq__Ações_Grupo__12M___2[[#This Row],[Fundos de investimento estrangeiro]]/1000 -> 0.93710661 | I2: =Cap__Líq__Ações_Grupo__12M___2[[#This Row],[Outros]]/1000 -> -0.71450564
A3: 45870 | B3: 485.78244 | C3: -1179.6197 | D3: 2180.8358 | E3: -515.43372 | F3: =Cap__Líq__Ações_Grupo__12M___2[[#This Row],[Ações (total)]]/1000 -> 0.48578244 | G3: =Cap__Líq__Ações_Grupo__12M___2[[#This Row],[Fundos ativos]]/1000 -> -1.1796197 | H3: =Cap__Líq__Ações_Grupo__12M___2[[#This Row],[Fundos de investimento estrangeiro]]/1000 -> 2.1808358 | I3: =Cap__Líq__Ações_Grupo__12M___2[[#This Row],[Outros]]/1000 -> -0.51543372
A4: 45901 | B4: -3665.7283 | C4: 2189.7243 | D4: -4831.667 | E4: -1023.7856 | F4: =Cap__Líq__Ações_Grupo__12M___2[[#This Row],[Ações (total)]]/1000 -> -3.6657283 | G4: =Cap__Líq__Ações_Grupo__12M___2[[#This Row],[Fundos ativos]]/1000 -> 2.1897243 | H4: =Cap__Líq__Ações_Grupo__12M___2[[#This Row],[Fundos de investimento estrangeiro]]/1000 -> -4.831667 | I4: =Cap__Líq__Ações_Grupo__12M___2[[#This Row],[Outros]]/1000 -> -1.0237856
A5: 45931 | B5: -1317.0536 | C5: -1355.9338 | D5: 386.26637 | E5: -347.38616 | F5: =Cap__Líq__Ações_Grupo__12M___2[[#This Row],[Ações (total)]]/1000 -> -1.3170536 | G5: =Cap__Líq__Ações_Grupo__12M___2[[#This Row],[Fundos ativos]]/1000 -> -1.3559338 | H5: =Cap__Líq__Ações_Grupo__12M___2[[#This Row],[Fundos de investimento estrangeiro]]/1000 -> 0.38626637 | I5: =Cap__Líq__Ações_Grupo__12M___2[[#This Row],[Outros]]/1000 -> -0.34738616
A6: 45962 | B6: 437.60403 | C6: -3630.6815 | D6: 4426.1103 | E6: -357.82483 | F6: =Cap__Líq__Ações_Grupo__12M___2[[#This Row],[Ações (total)]]/1000 -> 0.43760403 | G6: =Cap__Líq__Ações_Grupo__12M___2[[#This Row],[Fundos ativos]]/1000 -> -3.6306815 | H6: =Cap__Líq__Ações_Grupo__12M___2[[#This Row],[Fundos de investimento estrangeiro]]/1000 -> 4.4261103 | I6: =Cap__Líq__Ações_Grupo__12M___2[[#This Row],[Outros]]/1000 -> -0.35782483
A7: 45992 | B7: 1688.8386 | C7: 172.37735 | D7: 1740.2188 | E7: -223.75752 | F7: =Cap__Líq__Ações_Grupo__12M___2[[#This Row],[Ações (total)]]/1000 -> 1.6888386 | G7: =Cap__Líq__Ações_Grupo__12M___2[[#This Row],[Fundos ativos]]/1000 -> 0.17237735 | H7: =Cap__Líq__Ações_Grupo__12M___2[[#This Row],[Fundos de investimento estrangeiro]]/1000 -> 1.7402188 | I7: =Cap__Líq__Ações_Grupo__12M___2[[#This Row],[Outros]]/1000 -> -0.22375752
A8: 46023 | B8: -1277.4033 | C8: -2460.7756 | D8: 1597.0172 | E8: -413.64484 | F8: =Cap__Líq__Ações_Grupo__12M___2[[#This Row],[Ações (total)]]/1000 -> -1.2774033 | G8: =Cap__Líq__Ações_Grupo__12M___2[[#This Row],[Fundos ativos]]/1000 -> -2.4607756 | H8: =Cap__Líq__Ações_Grupo__12M___2[[#This Row],[Fundos de investimento estrangeiro]]/1000 -> 1.5970172 | I8: =Cap__Líq__Ações_Grupo__12M___2[[#This Row],[Outros]]/1000 -> -0.41364484
A9: 46054 | B9: -3635.1199 | C9: -4778.3765 | D9: 6492.9419 | E9: -5349.6853 | F9: =Cap__Líq__Ações_Grupo__12M___2[[#This Row],[Ações (total)]]/1000 -> -3.6351199 | G9: =Cap__Líq__Ações_Grupo__12M___2[[#This Row],[Fundos ativos]]/1000 -> -4.7783765 | H9: =Cap__Líq__Ações_Grupo__12M___2[[#This Row],[Fundos de investimento estrangeiro]]/1000 -> 6.4929419 | I9: =Cap__Líq__Ações_Grupo__12M___2[[#This Row],[Outros]]/1000 -> -5.3496853
A10: 46082 | B10: -795.44281 | C10: -2233.3152 | D10: 3467.3461 | E10: -2029.4738 | F10: =Cap__Líq__Ações_Grupo__12M___2[[#This Row],[Ações (total)]]/1000 -> -0.79544281 | G10: =Cap__Líq__Ações_Grupo__12M___2[[#This Row],[Fundos ativos]]/1000 -> -2.2333152 | H10: =Cap__Líq__Ações_Grupo__12M___2[[#This Row],[Fundos de investimento estrangeiro]]/1000 -> 3.4673461 | I10: =Cap__Líq__Ações_Grupo__12M___2[[#This Row],[Outros]]/1000 -> -2.0294738
A11: 46113 | B11: -159.62027 | C11: 670.47381 | D11: -355.41539 | E11: -474.67869 | F11: =Cap__Líq__Ações_Grupo__12M___2[[#This Row],[Ações (total)]]/1000 -> -0.15962027 | G11: =Cap__Líq__Ações_Grupo__12M___2[[#This Row],[Fundos ativos]]/1000 -> 0.67047381 | H11: =Cap__Líq__Ações_Grupo__12M___2[[#This Row],[Fundos de investimento estrangeiro]]/1000 -> -0.35541539 | I11: =Cap__Líq__Ações_Grupo__12M___2[[#This Row],[Outros]]/1000 -> -0.47467869
A12: 46143 | B12: -695.37602 | C12: -598.00498 | D12: 233.66546 | E12: -331.0365 | F12: =Cap__Líq__Ações_Grupo__12M___2[[#This Row],[Ações (total)]]/1000 -> -0.69537602 | G12: =Cap__Líq__Ações_Grupo__12M___2[[#This Row],[Fundos ativos]]/1000 -> -0.59800498 | H12: =Cap__Líq__Ações_Grupo__12M___2[[#This Row],[Fundos de investimento estrangeiro]]/1000 -> 0.23366546 | I12: =Cap__Líq__Ações_Grupo__12M___2[[#This Row],[Outros]]/1000 -> -0.3310365
A13: 46174 | B13: 21.092855 | C13: -1643.5967 | D13: 409.02921 | E13: 1255.6604 | F13: =Cap__Líq__Ações_Grupo__12M___2[[#This Row],[Ações (total)]]/1000 -> 0.021092855 | G13: =Cap__Líq__Ações_Grupo__12M___2[[#This Row],[Fundos ativos]]/1000 -> -1.6435967 | H13: =Cap__Líq__Ações_Grupo__12M___2[[#This Row],[Fundos de investimento estrangeiro]]/1000 -> 0.40902921 | I13: =Cap__Líq__Ações_Grupo__12M___2[[#This Row],[Outros]]/1000 -> 1.2556604

Sheet Cap  Líq  por Classe (12M)
A1: Período | B1: Renda Fixa | C1: Ações | D1: Multimercados | E1: Previdência | F1: ETF | G1: Renda Fixa (bi) | H1: Ações (bi) | I1: Multimercado (bi)
A2: 45839 | B2: 14261.665 | C2: -5157.0561 | D2: 6129.1964 | E2: 3643.0503 | F2: -1188.4157 | G2: =Cap__Líq__por_Classe__12M[[#This Row],[Renda Fixa]]/1000 -> 14.261665 | H2: =Cap__Líq__por_Classe__12M[[#This Row],[Ações]]/1000 -> -5.1570561 | I2: =Cap__Líq__por_Classe__12M[[#This Row],[Multimercados]]/1000 -> 6.1291964
A3: 45870 | B3: -7458.452 | C3: 485.78244 | D3: 5514.5503 | E3: -4710.737 | F3: 998.35093 | G3: =Cap__Líq__por_Classe__12M[[#This Row],[Renda Fixa]]/1000 -> -7.458452 | H3: =Cap__Líq__por_Classe__12M[[#This Row],[Ações]]/1000 -> 0.48578244 | I3: =Cap__Líq__por_Classe__12M[[#This Row],[Multimercados]]/1000 -> 5.5145503
A4: 45901 | B4: 50071.232 | C4: -3665.7283 | D4: -3582.7615 | E4: -5553.4986 | F4: 2574.7422 | G4: =Cap__Líq__por_Classe__12M[[#This Row],[Renda Fixa]]/1000 -> 50.071232 | H4: =Cap__Líq__por_Classe__12M[[#This Row],[Ações]]/1000 -> -3.6657283 | I4: =Cap__Líq__por_Classe__12M[[#This Row],[Multimercados]]/1000 -> -3.5827615
A5: 45931 | B5: 12828.317 | C5: -1317.0536 | D5: -3080.097 | E5: 3204.8339 | F5: 1422.2036 | G5: =Cap__Líq__por_Classe__12M[[#This Row],[Renda Fixa]]/1000 -> 12.828317 | H5: =Cap__Líq__por_Classe__12M[[#This Row],[Ações]]/1000 -> -1.3170536 | I5: =Cap__Líq__por_Classe__12M[[#This Row],[Multimercados]]/1000 -> -3.080097
A6: 45962 | B6: -4440.4167 | C6: 437.60403 | D6: 7391.2105 | E6: -8760.528 | F6: 5735.7918 | G6: =Cap__Líq__por_Classe__12M[[#This Row],[Renda Fixa]]/1000 -> -4.4404167 | H6: =Cap__Líq__por_Classe__12M[[#This Row],[Ações]]/1000 -> 0.43760403 | I6: =Cap__Líq__por_Classe__12M[[#This Row],[Multimercados]]/1000 -> 7.3912105
A7: 45992 | B7: -67627.253 | C7: 1688.8386 | D7: 7093.9046 | E7: -93.140872 | F7: 8539.8351 | G7: =Cap__Líq__por_Classe__12M[[#This Row],[Renda Fixa]]/1000 -> -67.627253 | H7: =Cap__Líq__por_Classe__12M[[#This Row],[Ações]]/1000 -> 1.6888386 | I7: =Cap__Líq__por_Classe__12M[[#This Row],[Multimercados]]/1000 -> 7.0939046
A8: 46023 | B8: 59516.226 | C8: -1277.4033 | D8: 20187.893 | E8: 1390.3039 | F8: 4701.0538 | G8: =Cap__Líq__por_Classe__12M[[#This Row],[Renda Fixa]]/1000 -> 59.516226 | H8: =Cap__Líq__por_Classe__12M[[#This Row],[Ações]]/1000 -> -1.2774033 | I8: =Cap__Líq__por_Classe__12M[[#This Row],[Multimercados]]/1000 -> 20.187893
A9: 46054 | B9: 56253.44 | C9: -3635.1199 | D9: -6249.4841 | E9: -1084.6561 | F9: 6622.6583 | G9: =Cap__Líq__por_Classe__12M[[#This Row],[Renda Fixa]]/1000 -> 56.25344 | H9: =Cap__Líq__por_Classe__12M[[#This Row],[Ações]]/1000 -> -3.6351199 | I9: =Cap__Líq__por_Classe__12M[[#This Row],[Multimercados]]/1000 -> -6.2494841
A10: 46082 | B10: 13575.535 | C10: -795.44281 | D10: -3230.0136 | E10: -279.55739 | F10: 6993.145 | G10: =Cap__Líq__por_Classe__12M[[#This Row],[Renda Fixa]]/1000 -> 13.575535 | H10: =Cap__Líq__por_Classe__12M[[#This Row],[Ações]]/1000 -> -0.79544281 | I10: =Cap__Líq__por_Classe__12M[[#This Row],[Multimercados]]/1000 -> -3.2300136
A11: 46113 | B11: -16649.929 | C11: -159.62027 | D11: -2600.0296 | E11: -2791.1217 | F11: 4209.072 | G11: =Cap__Líq__por_Classe__12M[[#This Row],[Renda Fixa]]/1000 -> -16.649929 | H11: =Cap__Líq__por_Classe__12M[[#This Row],[Ações]]/1000 -> -0.15962027 | I11: =Cap__Líq__por_Classe__12M[[#This Row],[Multimercados]]/1000 -> -2.6000296
A12: 46143 | B12: -3564.3098 | C12: -695.37602 | D12: -3708.3797 | E12: -1876.756 | F12: 4057.0403 | G12: =Cap__Líq__por_Classe__12M[[#This Row],[Renda Fixa]]/1000 -> -3.5643098 | H12: =Cap__Líq__por_Classe__12M[[#This Row],[Ações]]/1000 -> -0.69537602 | I12: =Cap__Líq__por_Classe__12M[[#This Row],[Multimercados]]/1000 -> -3.7083797
A13: 46174 | B13: -685.12905 | C13: 21.092855 | D13: -14277.738 | E13: -3941.1214 | F13: 5899.4554 | G13: =Cap__Líq__por_Classe__12M[[#This Row],[Renda Fixa]]/1000 -> -0.68512905 | H13: =Cap__Líq__por_Classe__12M[[#This Row],[Ações]]/1000 -> 0.021092855 | I13: =Cap__Líq__por_Classe__12M[[#This Row],[Multimercados]]/1000 -> -14.277738

Sheet PL por Classe (12M)
A1: Período | B1: Renda Fixa | C1: Ações | D1: Multimercados | E1: Renda Fixa (tri) | F1: Ações (tri) | G1: Multimercado (tri)
A2: 45839 | B2: 4300260.7 | C2: 615331.44 | D2: 1616369.6 | E2: =PL_por_Classe__12M[[#This Row],[Renda Fixa]]/1000000 -> 4.3002607 | F2: =PL_por_Classe__12M[[#This Row],[Ações]]/1000000 -> 0.61533144 | G2: =PL_por_Classe__12M[[#This Row],[Multimercados]]/1000000 -> 1.6163696
A3: 45870 | B3: 4346640.9 | C3: 645231.67 | D3: 1623781.5 | E3: =PL_por_Classe__12M[[#This Row],[Renda Fixa]]/1000000 -> 4.3466409 | F3: =PL_por_Classe__12M[[#This Row],[Ações]]/1000000 -> 0.64523167 | G3: =PL_por_Classe__12M[[#This Row],[Multimercados]]/1000000 -> 1.6237815
A4: 45901 | B4: 4438019.1 | C4: 660128.11 | D4: 1647632 | E4: =PL_por_Classe__12M[[#This Row],[Renda Fixa]]/1000000 -> 4.4380191 | F4: =PL_por_Classe__12M[[#This Row],[Ações]]/1000000 -> 0.66012811 | G4: =PL_por_Classe__12M[[#This Row],[Multimercados]]/1000000 -> 1.647632
A5: 45931 | B5: 4485232.5 | C5: 663157.15 | D5: 1654037 | E5: =PL_por_Classe__12M[[#This Row],[Renda Fixa]]/1000000 -> 4.4852325 | F5: =PL_por_Classe__12M[[#This Row],[Ações]]/1000000 -> 0.66315715 | G5: =PL_por_Classe__12M[[#This Row],[Multimercados]]/1000000 -> 1.654037
A6: 45962 | B6: 4527781.2 | C6: 689664.78 | D6: 1667994.9 | E6: =PL_por_Classe__12M[[#This Row],[Renda Fixa]]/1000000 -> 4.5277812 | F6: =PL_por_Classe__12M[[#This Row],[Ações]]/1000000 -> 0.68966478 | G6: =PL_por_Classe__12M[[#This Row],[Multimercados]]/1000000 -> 1.6679949
A7: 45992 | B7: 4505507.7 | C7: 692428.21 | D7: 1689083.7 | E7: =PL_por_Classe__12M[[#This Row],[Renda Fixa]]/1000000 -> 4.5055077 | F7: =PL_por_Classe__12M[[#This Row],[Ações]]/1000000 -> 0.69242821 | G7: =PL_por_Classe__12M[[#This Row],[Multimercados]]/1000000 -> 1.6890837
A8: 46023 | B8: 4618687.7 | C8: 732674.96 | D8: 1651345.7 | E8: =PL_por_Classe__12M[[#This Row],[Renda Fixa]]/1000000 -> 4.6186877 | F8: =PL_por_Classe__12M[[#This Row],[Ações]]/1000000 -> 0.73267496 | G8: =PL_por_Classe__12M[[#This Row],[Multimercados]]/1000000 -> 1.6513457
A9: 46054 | B9: 4714041 | C9: 738493.94 | D9: 1597601.7 | E9: =PL_por_Classe__12M[[#This Row],[Renda Fixa]]/1000000 -> 4.714041 | F9: =PL_por_Classe__12M[[#This Row],[Ações]]/1000000 -> 0.73849394 | G9: =PL_por_Classe__12M[[#This Row],[Multimercados]]/1000000 -> 1.5976017
A10: 46082 | B10: 4817921.9 | C10: 723615.65 | D10: 1604587.2 | E10: =PL_por_Classe__12M[[#This Row],[Renda Fixa]]/1000000 -> 4.8179219 | F10: =PL_por_Classe__12M[[#This Row],[Ações]]/1000000 -> 0.72361565 | G10: =PL_por_Classe__12M[[#This Row],[Multimercados]]/1000000 -> 1.6045872
A11: 46113 | B11: 4792873.9 | C11: 733002.78 | D11: 1600926.6 | E11: =PL_por_Classe__12M[[#This Row],[Renda Fixa]]/1000000 -> 4.7928739 | F11: =PL_por_Classe__12M[[#This Row],[Ações]]/1000000 -> 0.73300278 | G11: =PL_por_Classe__12M[[#This Row],[Multimercados]]/1000000 -> 1.6009266
A12: 46143 | B12: 4734794.4 | C12: 689794.61 | D12: 1563300.7 | E12: =PL_por_Classe__12M[[#This Row],[Renda Fixa]]/1000000 -> 4.7347944 | F12: =PL_por_Classe__12M[[#This Row],[Ações]]/1000000 -> 0.68979461 | G12: =PL_por_Classe__12M[[#This Row],[Multimercados]]/1000000 -> 1.5633007
A13: 46174 | B13: 4742303.2 | C13: 681503.23 | D13: 1544815 | E13: =PL_por_Classe__12M[[#This Row],[Renda Fixa]]/1000000 -> 4.7423032 | F13: =PL_por_Classe__12M[[#This Row],[Ações]]/1000000 -> 0.68150323 | G13: =PL_por_Classe__12M[[#This Row],[Multimercados]]/1000000 -> 1.544815

Sheet sector_performance
A1: data | B1: Utilities & Energy | C1: Homebuilders | D1: Income Properties | E1: Retail | F1: Metals & Mining | G1: Food & Beverages | H1: Education | I1: Pulp & Paper | J1: Transportation | K1: Financials Non-Banks | L1: Banks | M1: TMT | N1: Oil, Gas & Petrochemicals | O1: Column15 | P1: Capital Goods | Q1: Sanitation | R1: Health Care | S1: Agribusiness | T1: Ibovespa
A2: 36528 | B2: 1 | F2: 1 | G2: 1 | I2: 1 | K2: 1 | L2: 1 | M2: 1 | N2: 1 | P2: 1 | T2: 1
A3: 36529 | B3: 1 | F3: 1 | G3: 1 | I3: 1 | K3: 1 | L3: 1 | M3: 1 | N3: 1 | P3: 1 | T3: 0.93626698
A4: 36530 | B4: 1.0128584 | F4: 0.9984426 | G4: 0.98368912 | I4: 1.0146092 | K4: 1.0714286 | L4: 1.0322471 | M4: 1.0351654 | N4: 0.99612625 | P4: 1.0192484 | T4: 0.95953928
A5: 36531 | B5: 0.96358356 | F5: 1.0448018 | G5: 1.0029585 | I5: 1.0184051 | K5: 1.0769231 | L5: 1.045415 | M5: 1.0019702 | N5: 0.98970918 | P5: 0.99578699 | T5: 0.951329
A6: 36532 | B6: 0.97609351 | F6: 1.0640744 | G6: 1.0067779 | I6: 1.0313126 | K6: 1.0824176 | L6: 1.0603591 | M6: 1.0452245 | N6: 0.99855434 | P6: 1.0260886 | T6: 0.96331955
A7: 36535 | B7: 1.0132376 | F7: 1.1742805 | G7: 1.0052319 | I7: 1.0904887 | K7: 1.1208791 | L7: 1.0969386 | M7: 1.1226354 | N7: 1.0169024 | P7: 1.0357632 | T7: 1.0054341
A8: 36536 | B8: 0.98806865 | F8: 1.1366984 | G8: 0.96189523 | I8: 1.085323 | K8: 1.1153846 | L8: 1.0625871 | M8: 1.1344136 | N8: 0.99314956 | P8: 0.99168777 | T8: 0.97885411
A9: 36537 | B9: 0.97550174 | F9: 1.1444224 | G9: 0.98355624 | I9: 1.0490802 | K9: 1.0879121 | L9: 1.0674466 | M9: 1.1640549 | N9: 0.97583645 | P9: 0.98482085 | T9: 0.98145304
A10: 36538 | B10: 0.98782975 | F10: 1.1332359 | G10: 0.97581071 | I10: 1.0201117 | K10: 1.0769231 | L10: 1.0851763 | M10: 1.3015914 | N10: 0.96790702 | P10: 0.99173921 | T10: 1.0217366
A11: 36539 | B11: 1.0123558 | F11: 1.1348745 | G11: 0.94507853 | I11: 1.0273787 | K11: 1.0769231 | L11: 1.1412222 | M11: 1.3376438 | N11: 0.97709801 | P11: 0.96423958 | T11: 1.0429415
A12: 36542 | B12: 1.0002322 | F12: 1.129491 | G12: 0.9760744 | I12: 1.0827579 | K12: 1.1263736 | L12: 1.1291646 | M12: 1.3774539 | N12: 0.97102827 | P12: 1.0055367 | T12: 1.066332
A13: 36543 | B13: 1.0126419 | F13: 1.1041435 | G13: 0.97220307 | I13: 1.0750949 | K13: 1.0879121 | L13: 1.1396489 | M13: 1.3823201 | N13: 0.97545646 | P13: 1.0193094 | T13: 1.0574719
... A81: 36643 | B81: 0.76260934 | F81: 0.8835422 | G81: 0.90979211 | I81: 0.89414494 | K81: 0.80885606 | L81: 0.94981188 | M81: 1.2232395 | N81: 0.98925679 | P81: 1.304495 | T81: 0.91199055
A82: 36644 | B82: 0.80004422 | F82: 0.919856 | G82: 0.934362 | I82: 0.92256107 | K82: 0.858717 | L82: 1.0022999 | M82: 1.2303307 | N82: 0.99705994 | P82: 1.3412202 | Q82: 1 | T82: 0.91772002
A83: 36648 | B83: 0.76379313 | F83: 0.92403192 | G83: 0.92594655 | I83: 0.89983362 | K83: 0.81439617 | L83: 0.9991781 | M83: 1.2790388 | N83: 1.0164388 | P83: 1.2423961 | Q83: 1 | T83: 0.91695216
A84: 36649 | B84: 0.75123106 | F84: 0.92211726 | G84: 0.88350218 | I84: 0.89585384 | K84: 0.80331596 | L84: 0.97838585 | M84: 1.235221 | N84: 1.0110556 | P84: 1.1787631 | Q84: 0.94584017 | T84: 0.89238039
A85: 36650 | B85: 0.75133351 | F85: 0.9255214 | G85: 0.89196635 | I85: 0.89047238 | K85: 0.78669558 | L85: 0.98443759 | M85: 1.2262961 | N85: 1.0092508 | P85: 1.1822537 | Q85: 0.93379123 | T85: 0.88417011
A86: 36651 | B86: 0.75172628 | F86: 0.9567646 | G86: 0.8410563 | I86: 0.9051291 | K86: 0.80885606 | L86: 0.97945751 | M86: 1.3131944 | N86: 1.0146918 | P86: 1.2287104 | Q86: 0.9398157 | T86: 0.89881867
A87: 36654 | B87: 0.73924108 | F87: 0.93181305 | G87: 0.81221089 | I87: 0.88723914 | K87: 0.80331596 | L87: 0.97215534 | M87: 1.3128114 | N87: 1.0107379 | P87: 1.2058794 | Q87: 0.90366896 | T87: 0.87950384
A88: 36655 | B88: 0.68962695 | F88: 0.92457119 | G88: 0.781669 | I88: 0.89157399 | K88: 0.78669558 | L88: 0.97141451 | M88: 1.2951127 | N88: 1.007666 | P88: 1.1956568 | Q88: 0.87414906 | T88: 0.86125222
A89: 36656 | B89: 0.70202535 | F89: 0.92206928 | G89: 0.7816005 | I89: 0.88197724 | K89: 0.78115547 | L89: 0.95765588 | M89: 1.2862703 | N89: 0.99028565 | P89: 1.1698881 | Q89: 0.8494488 | T89: 0.85251034
A90: 36657 | B90: 0.70221082 | F90: 0.90899455 | G90: 0.80362501 | I90: 0.87237579 | K90: 0.78669558 | L90: 0.96221979 | M90: 1.2473809 | N90: 0.96470882 | P90: 1.1478124 | Q90: 0.85547328 | T90: 0.85634968
A91: 36658 | B91: 0.7145507 | F91: 0.90448383 | G91: 0.80362501 | I91: 0.87096352 | K91: 0.78115547 | L91: 0.93433902 | M91: 1.1563442 | N91: 0.9653759 | P91: 1.1249523 | Q91: 0.8433641 | T91: 0.85398701
A92: 36661 | B92: 0.75204392 | F92: 0.92523924 | G92: 0.86129269 | I92: 0.9005711 | K92: 0.83101648 | L92: 0.96380545 | M92: 1.2089154 | N92: 0.99316193 | P92: 1.2103155 | Q92: 0.89162002 | T92: 0.88924985
A93: 36662 | B93: 0.75222998 | F93: 0.97572692 | G93: 0.91643032 | I93: 0.91256914 | K93: 0.8531769 | L93: 0.98812968 | M93: 1.213439 | N93: 1.0214915 | P93: 1.1893064 | Q93: 0.9005362 | T93: 0.90726521
... A1571: 38834 | B1571: 2.3002905 | F1571: 11.560634 | G1571: 6.1957701 | I1571: 3.9908402 | K1571: 7.4580568 | L1571: 8.0759563 | M1571: 0.038046435 | N1571: 5.070989 | P1571: 4.3080776 | Q1571: 2.0453115 | T1571: 2.3479622
A1572: 38835 | B1572: 2.3316379 | F1572: 11.803401 | G1572: 6.1760555 | I1572: 4.0129771 | J1572: 1 | K1572: 7.6177582 | L1572: 8.0749716 | M1572: 0.038447622 | N1572: 5.137297 | P1572: 4.2155577 | Q1572: 2.0967012 | T1572: 2.384111
A1573: 38839 | B1573: 2.3870684 | F1573: 12.159339 | G1573: 6.3008877 | I1573: 4.067448 | J1573: 1 | K1573: 7.8896915 | L1573: 8.2185719 | M1573: 0.037716351 | N1573: 5.2379146 | P1573: 4.1653026 | Q1573: 2.1479882 | T1573: 2.4226816
A1574: 38840 | B1574: 2.4002485 | F1574: 12.060201 | G1574: 6.3723471 | I1574: 4.1264947 | J1574: 0.97894737 | K1574: 8.0255829 | L1574: 8.2402085 | M1574: 0.038110496 | N1574: 5.2386068 | P1574: 4.15692 | Q1574: 2.1193127 | T1574: 2.4169522
A1575: 38841 | B1575: 2.3588414 | F1575: 12.123455 | G1575: 6.3941306 | I1575: 4.2178762 | J1575: 0.93947368 | K1575: 8.2733847 | L1575: 8.3009786 | M1575: 0.037844672 | N1575: 5.2180308 | P1575: 4.0835817 | Q1575: 2.1440109 | T1575: 2.4202599
A1576: 38842 | B1576: 2.372957 | F1576: 12.256303 | G1576: 6.5649578 | I1576: 4.4073745 | J1576: 0.96315789 | K1576: 8.3533208 | L1576: 8.4235589 | M1576: 0.037757381 | N1576: 5.28291 | P1576: 4.1047889 | Q1576: 2.191095 | T1576: 2.4463674
A1577: 38845 | B1577: 2.3036431 | F1577: 12.352527 | G1577: 6.5195524 | I1577: 4.3930205 | J1577: 0.99473684 | K1577: 8.5371738 | L1577: 8.5648258 | M1577: 0.037228961 | N1577: 5.3259117 | P1577: 4.1291327 | Q1577: 2.285999 | T1577: 2.4521559
A1578: 38846 | B1578: 2.2758728 | F1578: 12.39072 | G1578: 6.4781725 | I1578: 4.4059283 | J1578: 1.0473684 | K1578: 8.513193 | L1578: 8.5770545 | M1578: 0.03803351 | N1578: 5.3947135 | P1578: 4.17474 | Q1578: 2.3018689 | T1578: 2.4795629
A1579: 38847 | B1579: 2.2893986 | F1579: 12.322761 | G1579: 6.5556074 | I1579: 4.2940026 | J1579: 1.0421053 | K1579: 8.2973655 | L1579: 8.4946243 | M1579: 0.038156171 | N1579: 5.3471623 | P1579: 4.2077522 | Q1579: 2.2805339 | T1579: 2.4660957
A1580: 38848 | B1580: 2.260907 | F1580: 12.167275 | G1580: 6.2159169 | I1580: 4.2341747 | J1580: 1.01 | K1580: 8.0735445 | L1580: 8.3553403 | M1580: 0.036427667 | N1580: 5.2660755 | P1580: 4.2154923 | Q1580: 2.20707 | T1580: 2.4126994
A1581: 38849 | B1581: 2.2053874 | F1581: 11.977153 | G1581: 6.2052436 | I1581: 4.123193 | J1581: 1 | K1581: 7.9776212 | L1581: 8.3127271 | M1581: 0.035308381 | N1581: 5.2120626 | P1581: 4.0688605 | Q1581: 2.1807954 | T1581: 2.3751329
A1582: 38852 | B1582: 2.218596 | F1582: 11.594437 | G1582: 5.9066155 | I1582: 4.0642897 | J1582: 0.98736842 | K1582: 7.7697874 | L1582: 8.0441405 | M1582: 0.034600439 | N1582: 5.1395533 | P1582: 3.9273719 | Q1582: 2.1545207 | T1582: 2.3196102
A1583: 38853 | B1583: 2.1916446 | F1583: 11.521161 | G1583: 6.0592754 | I1583: 4.042554 | J1583: 1 | K1583: 7.8337363 | L1583: 8.0956538 | M1583: 0.034754913 | N1583: 5.1712505 | P1583: 3.9875683 | Q1583: 2.1597757 | T1583: 2.3281748
... A1658: 38959 | B1658: 2.2731258 | F1658: 10.406201 | G1658: 6.1051588 | I1658: 3.9657724 | J1658: 1.1138594 | K1658: 7.332302 | L1658: 7.4301333 | M1658: 0.030633965 | N1658: 4.7942714 | P1658: 4.3371775 | Q1658: 2.4382869 | T1658: 2.1448907
A1659: 38960 | B1659: 2.3146217 | E1659: 1 | F1659: 10.321396 | G1659: 6.1827522 | I1659: 3.8595085 | J1659: 1.1350499 | K1659: 7.2840102 | L1659: 7.4048142 | M1659: 0.030418102 | N1659: 4.8016559 | P1659: 4.4136365 | Q1659: 2.4700266 | T1659: 2.1401063
A1660: 38961 | B1660: 2.3976727 | E1660: 1 | F1660: 10.726473 | G1660: 6.4454358 | I1660: 3.9262173 | J1660: 1.1709107 | K1660: 7.5254691 | L1660: 7.6856078 | M1660: 0.031360227 | N1660: 4.8728235 | P1660: 4.4529751 | Q1660: 2.5833229 | T1660: 2.2049025
A1661: 38964 | B1661: 2.4552884 | E1661: 1.0282721 | F1661: 10.897246 | G1661: 6.6571325 | I1661: 3.9594722 | J1661: 1.2035779 | K1661: 7.5818095 | L1661: 7.7299068 | M1661: 0.030785901 | N1661: 4.9188326 | P1661: 4.5710363 | Q1661: 2.6905234 | T1661: 2.2264028
A1662: 38965 | B1662: 2.4264147 | E1662: 1.0148669 | F1662: 10.905686 | G1662: 6.5130441 | I1662: 4.0351804 | J1662: 1.1786872 | K1662: 7.5013232 | L1662: 7.5796711 | M1662: 0.030527069 | N1662: 4.8452099 | P1662: 4.4476079 | Q1662: 2.5854249 | T1662: 2.2071471
A1663: 38966 | B1663: 2.3831989 | E1663: 1.0074476 | F1663: 10.706198 | G1663: 6.3807062 | I1663: 4.0244569 | J1663: 1.1712708 | K1663: 7.3564478 | L1663: 7.4397304 | M1663: 0.02982054 | N1663: 4.7301268 | P1663: 4.4350559 | Q1663: 2.5538953 | T1663: 2.1682812
A1664: 38968 | B1664: 2.3829963 | E1664: 1.0408856 | F1664: 10.563193 | G1664: 6.384979 | I1664: 3.9780581 | J1664: 1.1850153 | K1664: 7.3162047 | L1664: 7.4679281 | M1664: 0.030268172 | N1664: 4.6319111 | P1664: 4.7091088 | Q1664: 2.5281462 | T1664: 2.1593621
A1665: 38971 | B1665: 2.3251595 | E1665: 0.98217473 | F1665: 10.188483 | G1665: 6.1944691 | I1665: 3.96337 | J1665: 1.1771543 | K1665: 7.1471835 | L1665: 7.3946832 | M1665: 0.030039236 | N1665: 4.4888013 | P1665: 4.6965568 | Q1665: 2.5223657 | T1665: 2.1129356
A1666: 38972 | B1666: 2.3250636 | E1666: 0.97400351 | F1666: 10.227384 | G1666: 6.2712744 | I1666: 3.9539633 | J1666: 1.1677073 | K1666: 7.396691 | L1666: 7.6676137 | M1666: 0.030823697 | N1666: 4.5176346 | P1666: 4.6379806 | Q1666: 2.5445415 | T1666: 2.1350266
A1667: 38973 | B1667: 2.2677631 | E1667: 0.99777123 | F1667: 10.32041 | G1667: 6.3055128 | I1667: 3.965426 | J1667: 1.1646579 | K1667: 7.4369341 | L1667: 7.7597124 | M1667: 0.03136405 | N1667: 4.6326967 | P1667: 4.6442566 | Q1667: 2.5612522 | T1667: 2.1588305
A1668: 38974 | B1668: 2.2814631 | E1668: 1.0259836 | F1668: 10.167489 | G1668: 6.3700993 | I1668: 3.9475393 | J1668: 1.180465 | K1668: 7.4047396 | L1668: 7.6619416 | M1668: 0.031617512 | N1668: 4.5042316 | P1668: 4.6128765 | Q1668: 2.5538953 | T1668: 2.13544
A1669: 38975 | B1669: 2.2387042 | E1669: 1.0334051 | F1669: 10.126798 | G1669: 6.4674912 | I1669: 3.921406 | J1669: 1.2040783 | K1669: 7.4530314 | L1669: 7.7075684 | M1669: 0.031836793 | N1669: 4.4740892 | P1669: 4.5814964 | Q1669: 2.5433854 | T1669: 2.1363851
A1670: 38978 | B1670: 2.2678675 | E1670: 1.07016 | F1670: 10.209779 | G1670: 6.3697963 | I1670: 3.8823474 | J1670: 1.2106293 | K1670: 7.4449828 | L1670: 7.7463108 | M1670: 0.031822147 | N1670: 4.5868336 | P1670: 4.6003244 | Q1670: 2.5959347 | T1670: 2.154873
... A1737: 39078 | B1737: 2.5274413 | E1737: 1.1079813 | F1737: 13.239174 | G1737: 7.7493191 | I1737: 4.8687913 | J1737: 1.403519 | K1737: 8.7807778 | L1737: 9.3404637 | M1737: 0.036133989 | N1737: 5.597457 | P1737: 4.6620688 | Q1737: 3.1109177 | T1737: 2.6300059
A1738: 39079 | B1738: 2.4891159 | C1738: 1 | E1738: 1.1209777 | F1738: 13.151607 | G1738: 7.6843095 | I1738: 4.7788329 | J1738: 1.4107109 | K1738: 8.9196366 | L1738: 9.4326733 | M1738: 0.036032941 | N1738: 5.6049892 | P1738: 4.6726644 | Q1738: 3.1318681 | T1738: 2.6268754
A1739: 39084 | B1739: 2.5103329 | C1739: 1 | E1739: 1.1488502 | F1739: 13.461051 | G1739: 7.8783222 | I1739: 4.9287712 | J1739: 1.4482641 | K1739: 9.0584954 | L1739: 9.6721888 | M1739: 0.036456075 | N1739: 5.7313327 | P1739: 4.6408776 | Q1739: 3.1678899 | T1739: 2.680567
A1740: 39085 | B1740: 2.5062482 | C1740: 1.0292683 | E1740: 1.1295762 | F1740: 12.986647 | G1740: 7.8585986 | I1740: 4.8476226 | J1740: 1.4360845 | K1740: 9.0911681 | L1740: 9.6106533 | M1740: 0.036173789 | N1740: 5.5510438 | P1740: 4.6620688 | Q1740: 3.1585905 | T1740: 2.6252215
A1741: 39086 | B1741: 2.485389 | C1741: 1.0517073 | E1741: 1.1423304 | F1741: 12.84236 | G1741: 7.9109587 | I1741: 4.8118747 | J1741: 1.4111903 | K1741: 9.1075044 | L1741: 9.6326287 | M1741: 0.035781302 | N1741: 5.4343147 | P1741: 4.6472349 | Q1741: 3.1311199 | T1741: 2.6000591
A1742: 39087 | B1742: 2.4398136 | C1742: 1.0487805 | E1742: 1.084259 | F1742: 12.314675 | G1742: 7.4598469 | I1742: 4.6570509 | J1742: 1.3733512 | K1742: 8.788946 | L1742: 9.2418457 | M1742: 0.034120482 | N1742: 5.2361805 | P1742: 4.4628713 | Q1742: 2.9822225 | T1742: 2.4952747
A1743: 39090 | B1743: 2.4256382 | C1743: 1.0990244 | E1743: 1.0896661 | F1743: 12.57051 | G1743: 7.5749883 | I1743: 4.7478401 | J1743: 1.3606939 | K1743: 9.0666636 | L1743: 9.47607 | M1743: 0.034457642 | N1743: 5.2988597 | P1743: 4.4819434 | Q1743: 2.8432659 | T1743: 2.5297696
A1744: 39091 | B1744: 2.3764995 | C1744: 1.0634146 | E1744: 1.0959003 | F1744: 12.341966 | G1744: 7.5201672 | I1744: 4.6479737 | J1744: 1.353775 | K1744: 8.7726096 | L1744: 9.3125225 | M1744: 0.033482872 | N1744: 5.1708265 | P1744: 4.4183698 | Q1744: 2.8202846 | T1744: 2.4811577
A1745: 39092 | B1745: 2.3852598 | C1745: 1.0243902 | E1745: 1.09578 | F1745: 12.639038 | G1745: 7.7352506 | I1745: 4.5817062 | J1745: 1.3413812 | K1745: 8.7807778 | L1745: 9.2362511 | M1745: 0.033726803 | N1745: 5.1475249 | P1745: 4.4713478 | Q1745: 2.7683363 | T1745: 2.5005907
A1746: 39093 | B1746: 2.3798643 | C1746: 0.99268293 | E1746: 1.0839064 | F1746: 12.723326 | G1746: 7.8421911 | I1746: 4.6340456 | J1746: 1.3698662 | K1746: 8.886964 | L1746: 9.3972485 | M1746: 0.033828942 | N1746: 5.184217 | P1746: 4.5031346 | Q1746: 2.7898211 | T1746: 2.520378
A1747: 39094 | B1747: 2.4120597 | C1747: 1.002439 | E1747: 1.1178074 | F1747: 12.931267 | G1747: 7.7763217 | I1747: 4.566736 | J1747: 1.3846977 | K1747: 8.9033003 | L1747: 9.5304544 | M1747: 0.034309838 | N1747: 5.1947723 | P1747: 4.4501566 | Q1747: 2.8009376 | T1747: 2.5454223
A1748: 39097 | B1748: 2.4152965 | C1748: 0.9902439 | E1748: 1.1151873 | F1748: 12.879922 | G1748: 7.5401041 | I1748: 4.5481952 | J1748: 1.3697281 | K1748: 8.9441411 | L1748: 9.561295 | M1748: 0.034106094 | N1748: 5.1711988 | P1748: 4.5243259 | Q1748: 2.8860218 | T1748: 2.5350856
A1749: 39098 | B1749: 2.3895482 | C1749: 0.96341463 | E1749: 1.1250222 | F1749: 12.798341 | G1749: 7.3284012 | I1749: 4.4750943 | J1749: 1.3899581 | K1749: 8.9033003 | L1749: 9.5465708 | M1749: 0.034084452 | N1749: 5.1043499 | P1749: 4.5349215 | Q1749: 2.8539549 | T1749: 2.517661
... A1888: 39302 | B1888: 2.9071439 | C1888: 1.1264545 | E1888: 1.2384499 | F1888: 19.781649 | G1888: 10.049621 | I1888: 5.2091995 | J1888: 1.4235771 | K1888: 10.670577 | L1888: 11.160371 | M1888: 0.044585089 | N1888: 6.0332301 | P1888: 4.9852126 | Q1888: 4.0532573 | T1888: 3.2629061
A1889: 39303 | B1889: 2.7713216 | C1889: 1.0961478 | D1889: 1 | E1889: 1.2090075 | F1889: 19.057536 | G1889: 9.5883545 | I1889: 5.0660217 | J1889: 1.4135041 | K1889: 10.340275 | L1889: 10.943648 | M1889: 0.043369676 | N1889: 5.7887211 | P1889: 5.0278212 | Q1889: 3.7342984 | T1889: 3.1559362
A1890: 39304 | B1890: 2.7257437 | C1890: 1.0961478 | D1890: 1 | E1890: 1.2120931 | F1890: 18.531012 | G1890: 9.4985493 | I1890: 4.9730806 | J1890: 1.393929 | K1890: 10.487076 | L1890: 10.944083 | M1890: 0.043004945 | N1890: 5.6760262 | P1890: 4.8509953 | Q1890: 3.8104039 | T1890: 3.1091553
A1891: 39307 | B1891: 2.7375267 | C1891: 1.1016561 | D1891: 1.103139 | E1891: 1.1894713 | F1891: 18.494344 | G1891: 9.6037465 | I1891: 4.92222 | J1891: 1.3605885 | K1891: 10.27605 | L1891: 10.805353 | M1891: 0.04286271 | N1891: 5.6988073 | P1891: 4.9532561 | Q1891: 3.7761992 | T1891: 3.0971057
A1892: 39308 | B1892: 2.6523337 | C1892: 1.0746655 | D1892: 1.0986547 | E1892: 1.1574191 | F1892: 17.778685 | G1892: 9.3270507 | I1892: 4.754288 | J1892: 1.3283898 | K1892: 10.221 | L1892: 10.608163 | M1892: 0.041426149 | N1892: 5.6068017 | P1892: 4.8957344 | Q1892: 3.5615647 | T1892: 3.0071471
A1893: 39309 | B1893: 2.6094156 | C1893: 1.0328025 | D1893: 0.94170404 | E1893: 1.0966628 | F1893: 17.011554 | G1893: 9.0350367 | I1893: 4.6283763 | J1893: 1.2919205 | K1893: 9.7714225 | L1893: 10.188667 | M1893: 0.041018395 | N1893: 5.4663232 | P1893: 4.4739087 | Q1893: 3.5743915 | T1893: 2.9111045
A1894: 39310 | B1894: 2.5486637 | C1894: 0.98598217 | D1894: 0.80269058 | E1894: 1.066421 | F1894: 16.619087 | G1894: 8.5928504 | I1894: 4.6772006 | J1894: 1.2374432 | K1894: 9.2943202 | L1894: 9.9985932 | M1894: 0.039981097 | N1894: 5.3007562 | P1894: 4.4739087 | Q1894: 3.5487379 | T1894: 2.8360898
A1895: 39311 | B1895: 2.5766672 | C1895: 1.0575898 | D1895: 0.84304933 | E1895: 1.0831775 | F1895: 16.897626 | G1895: 8.8863426 | I1895: 4.60077 | J1895: 1.248177 | K1895: 9.6246218 | L1895: 10.103939 | M1895: 0.040552773 | N1895: 5.2571002 | P1895: 4.623039 | Q1895: 3.549593 | T1895: 2.868163
A1896: 39314 | B1896: 2.6653916 | C1896: 1.0465732 | D1896: 0.80269058 | E1896: 1.0769371 | F1896: 17.139388 | G1896: 9.2202464 | I1896: 4.6724514 | J1896: 1.2395938 | K1896: 10.012778 | L1896: 10.341425 | M1896: 0.040405515 | N1896: 5.3047987 | P1896: 4.5165174 | Q1896: 3.7915913 | T1896: 2.9064383
A1897: 39315 | B1897: 2.7091278 | C1897: 1.0630981 | D1897: 0.84753363 | E1897: 1.0963023 | F1897: 17.468546 | G1897: 9.4687723 | I1897: 4.7512442 | J1897: 1.2519293 | K1897: 10.224835 | L1897: 10.423205 | M1897: 0.040941585 | N1897: 5.3137432 | P1897: 4.3290393 | Q1897: 3.9070322 | T1897: 2.9424099
A1898: 39316 | B1898: 2.7531861 | C1898: 1.057039 | D1898: 0.94170404 | E1898: 1.1262751 | F1898: 18.430053 | G1898: 9.5490865 | I1898: 4.9506339 | J1898: 1.2478007 | K1898: 10.60285 | L1898: 10.738843 | M1898: 0.042963981 | N1898: 5.5746511 | P1898: 4.3801697 | Q1898: 3.9557739 | T1898: 3.0563497
A1899: 39317 | B1899: 2.6985187 | C1899: 1.0135236 | D1899: 0.97757848 | E1899: 1.1019188 | F1899: 18.672915 | G1899: 9.7004422 | I1899: 4.8690036 | J1899: 1.231377 | K1899: 10.648949 | L1899: 10.634943 | M1899: 0.043670235 | N1899: 5.5904005 | P1899: 4.3673871 | Q1899: 3.9762967 | T1899: 3.0624926
A1900: 39318 | B1900: 2.7667939 | C1900: 0.99699873 | D1900: 1.1883408 | E1900: 1.1175017 | F1900: 19.190293 | G1900: 9.8604125 | I1900: 5.04335 | J1900: 1.2739389 | K1900: 10.695049 | L1900: 10.841656 | M1900: 0.044576417 | N1900: 5.6808777 | P1900: 4.3673871 | Q1900: 4.0575329 | T1900: 3.1303603
... A2557: 40297 | B2557: 3.4906743 | C2557: 1.1469661 | D2557: 0.84007293 | E2557: 1.3276428 | F2557: 27.490472 | G2557: 12.494155 | I2557: 3.6095755 | J2557: 0.99168722 | K2557: 11.716496 | L2557: 14.447257 | M2557: 0.03934578 | N2557: 7.7932585 | P2557: 2.3841092 | Q2557: 3.2398879 | T2557: 4.0152392
A2558: 40298 | B2558: 3.4761924 | C2558: 1.174541 | D2558: 0.84007293 | E2558: 1.3581017 | F2558: 26.799986 | G2558: 12.624045 | I2558: 3.5822615 | J2558: 1.0020862 | K2558: 11.577489 | L2558: 14.412294 | M2558: 0.040572558 | N2558: 7.7647355 | P2558: 2.3555377 | Q2558: 3.2282823 | S2558: 1 | T2558: 3.9887183
A2559: 40301 | B2559: 3.4866185 | C2559: 1.2180616 | D2559: 0.84007293 | E2559: 1.3859892 | F2559: 26.259121 | G2559: 12.616699 | I2559: 3.5916966 | J2559: 1.004572 | K2559: 11.566609 | L2559: 14.357293 | M2559: 0.04075674 | N2559: 7.5049102 | P2559: 2.3717032 | Q2559: 3.3859246 | S2559: 1 | T2559: 3.9645009
A2560: 40302 | B2560: 3.4097262 | C2560: 1.1875825 | D2560: 0.84007293 | E2560: 1.354553 | F2560: 25.087654 | G2560: 12.387014 | I2560: 3.4456992 | J2560: 0.98276624 | K2560: 11.162245 | L2560: 13.917508 | M2560: 0.039348945 | N2560: 7.2421487 | P2560: 2.3416816 | Q2560: 3.2930801 | S2560: 0.95689655 | T2560: 3.8316007
A2561: 40303 | B2561: 3.3703821 | C2561: 1.1792154 | D2561: 0.84007293 | E2561: 1.3574024 | F2561: 25.423234 | G2561: 12.242142 | I2561: 3.4375993 | J2561: 0.97630946 | K2561: 11.245178 | L2561: 13.929903 | M2561: 0.039536205 | N2561: 7.189063 | P2561: 2.3001133 | Q2561: 3.2698689 | S2561: 0.93965517 | T2561: 3.8342587
A2562: 40304 | B2562: 3.2971874 | C2562: 1.1156309 | D2562: 0.84007293 | E2562: 1.324359 | F2562: 24.889443 | G2562: 12.10132 | I2562: 3.3198447 | J2562: 0.93078985 | K2562: 11.042915 | L2562: 13.817756 | M2562: 0.038949029 | N2562: 7.0584422 | P2562: 2.2724011 | Q2562: 3.2447236 | S2562: 0.87931034 | T2562: 3.7456586
A2563: 40305 | B2563: 3.3289632 | C2563: 1.0913911 | D2563: 0.84007293 | E2563: 1.3084128 | F2563: 24.586053 | G2563: 11.937883 | I2563: 3.2443049 | J2563: 0.92523195 | K2563: 11.064909 | L2563: 13.734937 | M2563: 0.038347986 | N2563: 7.0176598 | P2563: 2.2954946 | Q2563: 3.129635 | S2563: 0.85344828 | T2563: 3.7135263
A2564: 40308 | B2564: 3.4329525 | C2564: 1.1802614 | D2564: 0.84007293 | E2564: 1.3484843 | F2564: 25.680923 | G2564: 12.21108 | I2564: 3.4066173 | J2564: 0.96503413 | K2564: 11.603355 | L2564: 14.235554 | M2564: 0.039366325 | N2564: 7.2316702 | P2564: 2.3024226 | Q2564: 3.1576818 | S2564: 0.90517241 | T2564: 3.8660366
A2565: 40309 | B2565: 3.3913612 | C2565: 1.1695846 | D2565: 0.84007293 | E2565: 1.3313038 | F2565: 25.276432 | G2565: 12.164099 | I2565: 3.2779705 | J2565: 0.94886479 | K2565: 11.327642 | L2565: 14.037081 | M2565: 0.040320869 | N2565: 7.0444988 | P2565: 2.2862572 | Q2565: 3.1924985 | S2565: 0.87068966 | T2565: 3.805316
A2566: 40310 | B2566: 3.4355435 | C2566: 1.1954307 | D2566: 0.84007293 | E2566: 1.3330464 | F2566: 25.400001 | G2566: 12.281042 | I2566: 3.4308279 | J2566: 0.95218707 | K2566: 11.743515 | L2566: 14.073119 | M2566: 0.040705117 | N2566: 7.1162127 | P2566: 2.3278255 | Q2566: 3.2592305 | S2566: 0.87068966 | T2566: 3.8525103
A2567: 40311 | B2567: 3.3987132 | C2567: 1.1459802 | D2567: 0.84007293 | E2567: 1.3465075 | F2567: 24.941917 | G2567: 12.559978 | I2567: 3.4246546 | J2567: 0.93951686 | K2567: 11.89055 | L2567: 13.869564 | M2567: 0.04165427 | N2567: 7.1169727 | P2567: 2.3001133 | Q2567: 3.3153241 | S2567: 0.87931034 | T2567: 3.8268163
A2568: 40312 | B2568: 3.3253688 | C2568: 1.0843197 | D2568: 0.84007293 | E2568: 1.2969755 | F2568: 24.239209 | G2568: 12.388432 | I2568: 3.3200571 | J2568: 0.92495231 | K2568: 11.6854 | L2568: 13.616067 | M2568: 0.041440368 | N2568: 7.0907909 | P2568: 2.3093507 | Q2568: 3.2543949 | S2568: 0.85344828 | T2568: 3.7455405
A2569: 40315 | B2569: 3.3464497 | C2569: 1.0532298 | D2569: 0.84007293 | E2569: 1.2995971 | F2569: 23.630267 | G2569: 12.42425 | I2569: 3.1857527 | J2569: 0.91060521 | K2569: 11.98795 | L2569: 13.689875 | M2569: 0.041465813 | N2569: 7.0101689 | P2569: 2.3024226 | Q2569: 3.2882444 | S2569: 0.81896552 | T2569: 3.71329
... A2724: 40541 | B2724: 3.6843865 | C2724: 1.343582 | D2724: 0.84007293 | E2724: 1.5973842 | F2724: 25.0947 | G2724: 14.617396 | I2724: 3.2043986 | J2724: 1.0355629 | K2724: 11.764124 | L2724: 15.77435 | M2724: 0.045197492 | N2724: 7.2180821 | P2724: 2.8028269 | Q2724: 4.3728744 | S2724: 0.87068966 | T2724: 4.0727702
A2725: 40542 | B2725: 3.685012 | C2725: 1.3515793 | D2725: 0.84007293 | E2725: 1.6101015 | F2725: 25.201514 | G2725: 14.729012 | I2725: 3.1930906 | J2725: 1.0315828 | K2725: 11.864432 | L2725: 15.908417 | M2725: 0.044908976 | N2725: 7.294049 | P2725: 2.7910007 | Q2725: 4.3131246 | R2725: 1 | S2725: 0.86206897 | T2725: 4.0935617
A2726: 40546 | B2726: 3.7347865 | C2726: 1.3607556 | D2726: 0.84007293 | E2726: 1.6407808 | F2726: 25.779545 | G2726: 14.760374 | I2726: 3.186103 | J2726: 1.0443194 | K2726: 12.046216 | L2726: 15.966174 | M2726: 0.04602987 | N2726: 7.2469919 | P2726: 2.8146532 | Q2726: 4.4468021 | R2726: 1 | S2726: 0.86206897 | T2726: 4.1324276
A2727: 40547 | B2727: 3.7828907 | C2727: 1.3398328 | D2727: 0.84007293 | E2727: 1.6329845 | F2727: 26.349452 | G2727: 14.762509 | I2727: 3.2138235 | J2727: 1.0462998 | K2727: 11.989748 | L2727: 16.071857 | M2727: 0.04640765 | N2727: 7.2432314 | P2727: 2.8690541 | Q2727: 4.4154081 | R2727: 0.96396396 | S2727: 0.85344828 | T2727: 4.1533963
A2728: 40548 | B2728: 3.8372897 | C2728: 1.3528904 | D2728: 0.84007293 | E2728: 1.6386296 | F2728: 26.770338 | G2728: 14.844632 | I2728: 3.205319 | J2728: 1.0515365 | K2728: 11.883376 | L2728: 16.314532 | M2728: 0.047308219 | N2728: 7.3521134 | P2728: 2.8832456 | Q2728: 4.5055391 | R2728: 0.97522523 | S2728: 0.86206897 | T2728: 4.199114
A2729: 40549 | B2729: 3.8007692 | C2729: 1.3384762 | D2729: 0.84007293 | E2729: 1.6053472 | F2729: 26.659893 | G2729: 14.803107 | I2729: 3.1811469 | J2729: 1.0417329 | K2729: 11.855362 | L2729: 15.987703 | M2729: 0.047347116 | N2729: 7.3257161 | P2729: 2.8974371 | Q2729: 4.4336369 | R2729: 0.9481982 | S2729: 0.87931034 | T2729: 4.1688128
A2730: 40550 | B2730: 3.8237818 | C2730: 1.331891 | D2730: 0.84007293 | E2730: 1.590499 | F2730: 26.615461 | G2730: 14.744821 | I2730: 3.1634407 | J2730: 1.0386621 | K2730: 11.596843 | L2730: 15.650021 | M2730: 0.047094456 | N2730: 7.2590663 | P2730: 2.8714193 | Q2730: 4.4559164 | R2730: 0.96396396 | S2730: 0.86206897 | T2730: 4.138039
A2731: 40553 | B2731: 3.7808781 | C2731: 1.318209 | D2731: 0.84007293 | E2731: 1.6005754 | F2731: 26.535644 | G2731: 14.785297 | I2731: 3.1878799 | J2731: 1.0291598 | K2731: 11.695577 | L2731: 15.707963 | M2731: 0.047740172 | N2731: 7.3044155 | P2731: 2.8856109 | Q2731: 4.4994629 | R2731: 0.98378378 | S2731: 0.87068966 | T2731: 4.1421737
A2732: 40554 | B2732: 3.7925879 | C2732: 1.3230079 | D2732: 0.84007293 | E2732: 1.6131541 | F2732: 26.816647 | G2732: 14.806082 | I2732: 3.2086413 | J2732: 1.0401633 | K2732: 11.500005 | L2732: 15.830002 | M2732: 0.048286983 | N2732: 7.3038677 | P2732: 2.8974371 | Q2732: 4.5217425 | R2732: 0.99774775 | S2732: 0.87068966 | T2732: 4.1596574
...

Sheet raw_sector
A1: Column1 | B1: sector | C1: sector_63d_adtv | D1: ytd_foreigners_flow | E1: ytd_foreigners_flow_to_63d_adtv | F1: ytd_retail_flow | G1: ytd_retail_flow_to_63d_adtv | H1: ytd_local_institutions_flow | I1: ytd_local_institutions_flow_to_63d_adtv | J1: ytd_others_flow | K1: ytd_others_flow_to_63d_adtv | L1: last_month_foreigners_flow | M1: last_month_foreigners_flow_to_63d_adtv | N1: last_month_retail_flow | O1: last_month_retail_flow_to_63d_adtv | P1: last_month_local_institutions_flow | Q1: last_month_local_institutions_flow_to_63d_adtv | R1: last_month_others_flow | S1: last_month_others_flow_to_63d_adtv | T1: mtd_foreigners_flow | U1: mtd_foreigners_flow_to_63d_adtv | V1: mtd_retail_flow | W1: mtd_retail_flow_to_63d_adtv | X1: mtd_local_institutions_flow | Y1: mtd_local_institutions_flow_to_63d_adtv | Z1: mtd_others_flow | AA1: mtd_others_flow_to_63d_adtv
A2: 0 | B2: Agribusiness | C2: 106879279 | D2: -3.9071934e+08 | E2: -3.6557071 | F2: 95058185 | G2: 0.8893977 | H2: 1.9147667e+08 | I2: 1.7915229 | J2: 1.041845e+08 | K2: 0.97478671 | L2: -2.6927775e+08 | M2: -2.519457 | N2: 40604094 | O2: 0.37990614 | P2: 2.195507e+08 | Q2: 2.0541933 | R2: 9122978.9 | S2: 0.085357788 | T2: -55075801 | U2: -0.5153085 | V2: 19360043 | W2: 0.18113935 | X2: 29943651 | Y2: 0.28016329 | Z2: 5772107 | AA2: 0.054005856
A3: 1 | B3: Banks | C3: 2796855002 | D3: 1.6164554e+09 | E3: 0.57795467 | F3: -1.5147628e+08 | G3: -0.054159505 | H3: -1.4520351e+09 | I3: -0.5191671 | J3: -12038916 | K3: -0.0043044477 | L3: -2.6749242e+09 | M3: -0.95640433 | N3: 4.781377e+08 | O3: 0.17095548 | P3: 2.2086009e+09 | Q3: 0.78967301 | R3: -10909233 | S3: -0.0039005357 | T3: 1.7413777e+09 | U3: 0.62261995 | V3: -3.3691632e+08 | W3: -0.12046256 | X3: -1.4202504e+09 | Y3: -0.50780265 | Z3: 15788961 | AA3: 0.0056452556
A4: 2 | B4: Capital Goods | C4: 776166889 | D4: -5.3946111e+08 | E4: -0.69503236 | F4: 4.7509485e+08 | G4: 0.61210399 | H4: -8.6728467e+08 | I4: -1.1173946 | J4: 9.3278667e+08 | K4: 1.2017862 | L4: -1.6572953e+08 | M4: -0.21352306 | N4: -1.5645552e+08 | O4: -0.20157459 | P4: 3.192077e+08 | Q4: 0.41126168 | R4: 4113096.1 | S4: 0.005299242 | T4: 4018617.8 | U4: 0.0051775177 | V4: -25149812 | W4: -0.032402583 | X4: 17226886 | Y4: 0.022194822 | Z4: 3904308.2 | AA4: 0.0050302431
A5: 3 | B5: Education | C5: 134772310 | D5: -5.3664284e+08 | E5: -3.9818479 | F5: 22795476 | G5: 0.16914065 | H5: 4.2282182e+08 | I5: 3.1373049 | J5: 91025543 | K5: 0.67540241 | L5: -54076631 | M5: -0.40124438 | N5: 19652494 | O5: 0.14581997 | P5: 30578871 | Q5: 0.22689283 | R5: 3845266.9 | S5: 0.028531579 | T5: 8373347.6 | U5: 0.062129585 | V5: -12351693 | W5: -0.091648597 | X5: 3555609.7 | Y5: 0.026382346 | Z5: 422735.89 | AA5: 0.0031366672
A6: 4 | B6: Financials Non-Banks | C6: 1311493554 | D6: 3.497645e+09 | E6: 2.6669174 | F6: 2.6813906e+08 | G6: 0.20445321 | H6: -3.9375186e+09 | I6: -3.0023164 | J6: 1.7239081e+08 | K6: 0.13144618 | L6: -1.1598501e+09 | M6: -0.88437347 | N6: -3.4171909e+08 | O6: -0.2605572 | P6: 1.5690518e+09 | Q6: 1.1963854 | R6: -66826385 | S6: -0.050954413 | T6: 2.4019422e+08 | U6: 0.18314556 | V6: -1.3720706e+08 | W6: -0.10461894 | X6: -1.449037e+08 | Y6: -0.11048754 | Z6: 41916538 | AA6: 0.031960918
A7: 5 | B7: Food & Beverages | C7: 546945002 | D7: -2.6955304e+09 | E7: -4.9283391 | F7: -4.3359636e+08 | G7: -0.79276044 | H7: 3.7634936e+08 | I7: 0.68809361 | J7: 2.7536408e+09 | K7: 5.0345845 | L7: -1.1466082e+09 | M7: -2.0963866 | N7: -68862268 | O7: -0.12590346 | P7: -1.1622303e+08 | Q7: -0.21249491 | R7: 1.3325569e+09 | S7: 2.4363635 | T7: -4.5539266e+08 | U7: -0.83261144 | V7: 96031089 | W7: 0.17557723 | X7: -10051290 | Y7: -0.018377149 | Z7: 3.6941286e+08 | AA7: 0.67541135
A8: 6 | B8: Health Care | C8: 459834923 | D8: -3.6884128e+09 | E8: -8.0211673 | F8: 1.1656779e+08 | G8: 0.25349921 | H8: 1.9930245e+09 | I8: 4.3342173 | J8: 1.5788206e+09 | K8: 3.4334507 | L8: -59250181 | M8: -0.12885098 | N8: 29722610 | O8: 0.064637566 | P8: -6.7887045e+08 | Q8: -1.4763351 | R8: 7.0839803e+08 | S8: 1.5405486 | T8: 1.7361087e+08 | U8: 0.37755043 | V8: -1715159.4 | W8: -0.003729946 | X8: -1.9073956e+08 | Y8: -0.41480008 | Z8: 18843847 | AA8: 0.040979591
A9: 7 | B9: Homebuilders | C9: 590096056 | D9: -1.6963768e+09 | E9: -2.8747469 | F9: 2.8764128e+08 | G9: 0.48744823 | H9: 1.2953e+09 | I9: 2.1950663 | J9: 1.134355e+08 | K9: 0.19223226 | L9: -72353666 | M9: -0.12261337 | N9: -96557683 | O9: -0.16363045 | P9: 1.191507e+08 | Q9: 0.20191747 | R9: 49760627 | S9: 0.084326317 | T9: -1.7491598e+08 | U9: -0.29641951 | V9: 69282397 | W9: 0.11740868 | X9: 99668716 | Y9: 0.16890253 | Z9: 5964870.4 | AA9: 0.010108304
A10: 8 | B10: Income Properties | C10: 337740128 | D10: -30748093 | E10: -0.091040687 | F10: 60909007 | G10: 0.18034282 | H10: -34131368 | I10: -0.10105808 | J10: 3981272.2 | K10: 0.011787975 | L10: -1.2254796e+08 | M10: -0.36284691 | N10: 46196397 | O10: 0.1367809 | P10: 68801243 | Q10: 0.2037106 | R10: 7561140.5 | S10: 0.022387451 | T10: 12184273 | U10: 0.036075881 | V10: 44886921 | W10: 0.13290373 | X10: -56859415 | Y10: -0.16835256 | Z10: -211778.81 | AA10: -0.00062704663
A11: 9 | B11: Metals & Mining | C11: 2025985401 | D11: 9.2707969e+09 | E11: 4.5759446 | F11: -6.0403242e+09 | G11: -2.9814253 | H11: -3.9715661e+09 | I11: -1.9603133 | J11: 7.4324312e+08 | K11: 0.36685512 | L11: -1.8661949e+08 | M11: -0.092112949 | N11: -1.3191797e+08 | O11: -0.065112991 | P11: -46400893 | Q11: -0.022902876 | R11: 3.6708805e+08 | S11: 0.18118988 | T11: -1.3950397e+09 | U11: -0.68857344 | V11: 37337419 | W11: 0.018429264 | X11: 1.3149073e+09 | Y11: 0.64902112 | Z11: 42794992 | AA11: 0.021123051
A12: 10 | B12: Oil, Gas & Petrochemicals | C12: 3710957819 | D12: 2.8928533e+10 | E12: 7.7954357 | F12: -1.2135809e+10 | G12: -3.2702634 | H12: -1.0236365e+10 | I12: -2.7584158 | J12: -6.5550346e+09 | K12: -1.7663997 | L12: 8.9538469e+08 | M12: 0.24128129 | N12: -21419726 | O12: -0.0057720208 | P12: 1.2727439e+09 | Q12: 0.34296912 | R12: -2.1453845e+09 | S12: -0.57812151 | T12: -4.5241208e+08 | U12: -0.12191248 | V12: -49638936 | W12: -0.013376314 | X12: 4.8493304e+08 | Y12: 0.13067598 | Z12: 17117979 | AA12: 0.0046128196
A13: 11 | B13: Pulp & Paper | C13: 342854272 | D13: 1.3825635e+08 | E13: 0.40325106 | F13: 6.7656161e+08 | G13: 1.9733212 | H13: -1.0275099e+09 | I13: -2.996929 | J13: 2.1353473e+08 | K13: 0.62281485 | L13: -73966722 | M13: -0.21573808 | N13: 1.5118714e+08 | O13: 0.44096618 | P13: -1.3667361e+08 | Q13: -0.39863471 | R13: 60295989 | S13: 0.17586478 | T13: 1.093423e+08 | U13: 0.3189177 | V13: -67606728 | W13: -0.19718794 | X13: -1.2758205e+08 | Y13: -0.37211743 | Z13: 85846482 | AA13: 0.25038767
... A18: 16 | B18: Utilities & Energy | C18: 1995240425 | D18: 6.3446986e+09 | E18: 3.1799168 | F18: 1.5903795e+08 | G18: 0.079708666 | H18: -4.5024127e+09 | I18: -2.2565765 | J18: -2.0004381e+09 | K18: -1.002605 | L18: 1.8187377e+08 | M18: 0.091153809 | N18: 3.0822409e+08 | O18: 0.15447967 | P18: -2.6885413e+08 | Q18: -0.13474774 | R18: -2.2035803e+08 | S18: -0.11044184 | T18: 5.6717889e+08 | U18: 0.28426594 | V18: -79376110 | W18: -0.03978273 | X18: -4.3377598e+08 | Y18: -0.21740537 | Z18: -54026801 | AA18: -0.02707784

Sheet raw_annual
A1: year | B1: foreign_secondary_cash | C1: foreign_primary_cash | D1: foreign_cash_consolidated | E1: foreign_futures | F1: foreign_total_cash_plus_futures
A2: 2008 | B2: -24.6297 | C2: 16.0655 | D2: -8.5642
A3: 2009 | B3: 20.5966 | C3: 30.066 | D3: 50.6626
A4: 2010 | B4: 5.958 | C4: 40.4714 | D4: 46.4294
A5: 2011 | B5: -1.3519 | C5: 9.8813 | D5: 8.5294
A6: 2012 | B6: 1.8222 | C6: 4.8275 | D6: 6.6497
A7: 2013 | B7: 11.7463 | C7: 9.9314 | D7: 21.6777
A8: 2014 | B8: 20.3426 | C8: 5.5208 | D8: 25.8634
A9: 2015 | B9: 16.387079 | C9: 11.984092 | D9: 28.371171
A10: 2016 | B10: 14.3254 | C10: 5.2161 | D10: 19.5415
A11: 2017 | B11: 14.354 | C11: 25.2008 | D11: 39.5548
A12: 2018 | B12: -11.5211 | C12: 6.6896 | D12: -4.8315 | E12: 0.576832 | F12: -4.254668
A13: 2019 | B13: -44.5174 | C13: 38.019 | D13: -6.4984 | E13: -4.194369 | F13: -10.692769
A14: 2020 | B14: -39.6635 | C14: 40.3646 | D14: 0.7012 | E14: 2.617767 | F14: 3.318967
A15: 2021 | B15: -7.1524 | C15: 48.6904 | D15: 41.538 | E15: 27.192255 | F15: 68.730255
A16: 2022 | B16: 100.8243 | C16: 18.9702 | D16: 119.7943 | E16: -1.863147 | F16: 117.93115
A17: 2023 | B17: 44.8534 | C17: 11.1016 | D17: 55.9545 | E17: 2.464804 | F17: 58.419304
A18: 2024 | B18: -32.1083 | C18: 7.9099 | D18: -24.1982 | E18: 5.26925 | F18: -18.92895
A19: 2025 | B19: 25.473 | C19: 1.3972 | D19: 26.8704 | E19: -7.873738 | F19: 18.996662
A20: 2026 | B20: 34.978485 | C20: 2.8828 | D20: 37.861285 | E20: -17.410939 | F20: 20.450346

Sheet raw_daily
A1: date | B1: financial_cash | C1: foreign_cash | D1: foreign_futures | E1: individual_cash | F1: individual_futures | G1: institutional_cash | H1: institutional_futures | I1: others_cash
A2: 44743 | D2: 0.21027685 | F2: -0.49786058 | H2: 0.38569494
A3: 44746 | D3: -0.80969713 | F3: 0.45290953 | H3: 0.29022143
A4: 44747 | D4: -0.38665766 | F4: -0.33992631 | H4: 0.75321342
A5: 44748 | D5: 0.266344 | F5: -0.12327736 | H5: -0.080835251
A6: 44749 | D6: -0.49690211 | F6: -0.59047084 | H6: 1.1826366
A7: 44750 | D7: -0.21328737 | F7: 0.53104525 | H7: -0.38446689
A8: 44753 | D8: 1.0266168 | F8: 0.52627508 | H8: -1.675201
A9: 44754 | D9: 0.35667412 | F9: -0.42838424 | H9: 0.13938523
A10: 44755 | D10: -0.38687022 | F10: 0.31123429 | H10: 0.094955685
A11: 44756 | D11: -0.37983102 | F11: 0.36617918 | H11: -0.12650984
A12: 44757 | D12: -0.62283584 | F12: -0.38601877 | H12: 1.0538103
A13: 44760 | D13: 2.5377646 | F13: -0.05461647 | H13: -2.4267923
... A203: 45036 | D203: 0.55334667 | F203: -0.23586615 | H203: -0.27362309
A204: 45040 | B204: 0.081842 | C204: 0.954207 | D204: 0.24608663 | E204: 0.211187 | F204: 0.10706852 | G204: -1.260841 | H204: -0.41813587 | I204: 0.013605
A205: 45041 | B205: 0.131298 | C205: -0.72845 | D205: -0.26836166 | E205: 0.474092 | F205: 0.056428417 | G205: 0.065984 | H205: 0.16655517 | I205: 0.057077
A206: 45042 | B206: 0.101896 | C206: -0.482399 | D206: -0.97871275 | E206: 0.330931 | F206: 0.48069279 | G206: 0.050159 | H206: 0.32689139 | I206: -0.000589
A207: 45043 | B207: -0.072364 | C207: -0.190486 | D207: -1.2956977 | E207: 0.641218 | F207: -0.11667316 | G207: -0.460217 | H207: 1.63149 | I207: 0.08185
A208: 45044 | B208: -0.090682 | C208: -0.239696 | D208: 0.027904304 | E208: -0.319354 | F208: -0.27893971 | G208: 0.517335 | H208: 0.2675555 | I208: 0.132397
A209: 45048 | B209: 0.1117 | C209: -1.293697 | D209: 0.12304714 | E209: 0.824971 | F209: 0.72572372 | G209: 0.183085 | H209: -1.0276643 | I209: 0.173942
A210: 45049 | B210: -0.032329 | C210: -0.387762 | D210: 0.38229968 | E210: 0.115582 | F210: -0.18023163 | G210: 0.133504 | H210: -0.12404041 | I210: 0.171004
A211: 45050 | B211: 0.05146 | C211: -0.527985 | D211: -1.213282 | E211: 0.041396 | F211: -0.37354964 | G211: 0.229811 | H211: 1.607407 | I211: 0.205319
A212: 45051 | B212: -0.132714 | C212: 0.156952 | D212: -0.003365809 | E212: -1.03624 | F212: -0.95115198 | G212: 0.820729 | H212: 1.079298 | I212: 0.191272
A213: 45054 | B213: -0.05743 | C213: 0.319465 | D213: -0.57000047 | E213: -0.277407 | F213: 0.02066151 | G213: -0.188101 | H213: 0.50982888 | I213: 0.203475
A214: 45055 | B214: -0.036094 | C214: 0.567175 | D214: 2.0796483 | E214: -0.402164 | F214: -0.57086276 | G214: -0.350858 | H214: -1.3173632 | I214: 0.221941
A215: 45056 | B215: 0.001586 | C215: 0.066505 | D215: -2.0996913 | E215: -0.089177 | F215: 0.25597225 | G215: -0.254329 | H215: 1.7721757 | I215: 0.275412
... A375: 45288 | B375: 0.138897 | C375: 0.087841 | D375: -0.46981129 | E375: -0.076187 | F375: 0.52656974 | G375: -0.184531 | H375: -0.10045754 | I375: 0.033981
A376: 45289 | B376: 0 | C376: 0 | E376: 0 | G376: 0 | I376: 0
A377: 45293 | B377: 0.119816 | C377: -0.508255 | D377: 0.76009666 | E377: 0.573754 | F377: 0.85842947 | G377: -0.235031 | H377: -1.3349823 | I377: 0.049716
A378: 45294 | B378: 0.125862 | C378: 1.279634 | D378: 0.70247903 | E378: -0.107644 | F378: -0.28428392 | G378: -1.259318 | H378: -0.36006087 | I378: -0.038534
A379: 45295 | B379: -0.837359 | C379: 1.015959 | D379: -1.0297433 | E379: 0.53205 | F379: 1.0002391 | G379: -0.839145 | H379: 0.7299562 | I379: 0.128495
A380: 45296 | B380: 0.354911 | C380: 0.145152 | D380: 0.21798419 | E380: -0.034056 | F380: -0.61221543 | G380: -0.528602 | H380: 0.31856284 | I380: 0.062595
A381: 45299 | B381: 0.05621 | C381: 1.294099 | D381: -0.4790872 | E381: -0.039359 | F381: -0.44297074 | G381: -1.391445 | H381: 0.62290489 | I381: 0.080495
A382: 45300 | B382: 0.274018 | C382: -0.659234 | D382: -1.8402988 | E382: 0.467702 | F382: 1.0571405 | G382: -0.140887 | H382: 0.9170351 | I382: 0.058401
A383: 45301 | B383: 0.041042 | C383: -0.564092 | D383: -0.57559272 | E383: 0.398758 | F383: 0.42140962 | G383: -0.015197 | H383: 0.15974921 | I383: 0.139489
A384: 45302 | B384: 0.477216 | C384: -0.060482 | D384: -1.7623874 | E384: 0.312365 | F384: -0.032549773 | G384: -0.845222 | H384: 1.7669442 | I384: 0.116123
A385: 45303 | B385: 0.016164 | C385: 0.321663 | D385: 0.35814086 | E385: 0.043696 | F385: -0.34867732 | G385: -0.536193 | H385: 0.018658532 | I385: 0.154671
A386: 45306 | B386: 0.081962 | C386: 0.079383 | D386: 0.29409941 | E386: -0.042063 | F386: -0.55767748 | G386: -0.189498 | H386: 0.33983041 | I386: 0.070215
A387: 45307 | B387: -0.036168 | C387: -1.668118 | D387: -1.6260821 | E387: 0.736549 | F387: 1.6505876 | G387: 0.84827 | H387: -0.1223061 | I387: 0.119469
A388: 45308 | B388: 0.429779 | C388: -0.734992 | D388: 0.69853089 | E388: 0.372766 | F388: 0.003765755 | G388: -0.195232 | H388: -0.6659736 | I388: 0.127678
... A624: 45649 | B624: -0.322063 | C624: -0.863727 | D624: 0.85517204 | E624: 0.416487 | F624: 0.40399186 | G624: 0.630022 | H624: -1.1476253 | I624: 0.13928
A625: 45650 | B625: 0 | C625: 0 | E625: 0 | G625: 0 | I625: 0
A626: 45652 | B626: 0.062171 | C626: 0.071048 | D626: 0.88220617 | E626: 0.093188 | F626: -0.2419465 | G626: -0.386574 | H626: -0.64041973 | I626: 0.160167
A627: 45653 | B627: 0.157018 | C627: -0.058842 | D627: -1.2345313 | E627: 0.356412 | F627: 0.28538293 | G627: -0.629799 | H627: 0.90796853 | I627: 0.175211
A628: 45656 | B628: 0.027531 | C628: -0.439008 | D628: 1.5667215 | E628: 0.229222 | F628: -0.097078857 | G628: 0.025137 | H628: -1.5323838 | I628: 0.157119
A629: 45657 | B629: 0 | C629: 0 | E629: 0 | G629: 0 | I629: 0
A630: 45659 | B630: 0.024915 | C630: -0.541266 | D630: -0.10123635 | E630: 0.328691 | F630: -0.022815259 | G630: 0.089303 | H630: 0.25251341 | I630: 0.098357
A631: 45660 | B631: 0.039109 | C631: -1.955165 | D631: -0.89338415 | E631: 0.501506 | F631: 0.71013513 | G631: 1.294218 | H631: 0.081163868 | I631: 0.120331
A632: 45663 | B632: 0.039095 | C632: -0.545991 | D632: 1.6417598 | E632: -0.105507 | F632: -0.87245155 | G632: 0.490116 | H632: -0.75429276 | I632: 0.122289
A633: 45664 | B633: -0.068478 | C633: 0.409862 | D633: 0.54040923 | E633: -0.000522 | F633: -0.55893925 | G633: -0.454677 | H633: 0.11854866 | I633: 0.113812
A634: 45665 | B634: 0.001449 | C634: -0.718172 | D634: -1.3993495 | E634: 0.423968 | F634: 0.89252254 | G634: 0.074725 | H634: 0.37653885 | I634: 0.218033
A635: 45666 | B635: 0.073293 | C635: -0.316197 | D635: 0.46987832 | E635: 0.049979 | F635: -0.081370173 | G635: 0.132454 | H635: -0.39348334 | I635: 0.060469
A636: 45667 | B636: 0.015796 | C636: -0.987889 | D636: 0.95777482 | E636: 0.124959 | F636: 0.10323937 | G636: 0.632571 | H636: -1.0029152 | I636: 0.214565
A637: 45670 | B637: 0.065882 | C637: -0.314142 | D637: 1.0389386 | E637: 0.09013 | F637: 0.056309987 | G637: 0.011826 | H637: -1.0608268 | I637: 0.146303
A638: 45671 | B638: -0.051886 | C638: -1.309219 | D638: -1.9508703 | E638: 0.172717 | F638: -0.28586195 | G638: 1.125759 | H638: 2.260972 | I638: 0.062628
A639: 45672 | B639: 0.228021 | C639: 0.465791 | D639: 1.7315819 | E639: -0.586668 | F639: -1.4521454 | G639: -0.113329 | H639: -0.1531607 | I639: 0.006184
A640: 45673 | B640: 0.223105 | C640: 6.512761 | D640: -0.16462742 | E640: 0.396923 | F640: 1.2703405 | G640: 1.888223 | H640: -1.250706 | I640: -9.02101
A641: 45674 | B641: -0.332476 | C641: 2.92027 | D641: 0.8954291 | E641: -0.132219 | F641: -0.36375083 | G641: -2.554421 | H641: -0.43594917 | I641: 0.098847
... A876: 46014 | B876: -0.621542 | C876: -0.122869 | D876: 0.47216244 | E876: 0.166768 | F876: -1.0572019 | G876: 0.651374 | H876: 0.554732 | I876: -0.073731
A877: 46015 | B877: 0 | C877: 0 | E877: 0 | G877: 0 | I877: 0
A878: 46017 | B878: 0.296238 | C878: 0.149878 | D878: -1.0457187 | E878: 0.357888 | F878: -0.30726793 | G878: -0.733033 | H878: 1.2768346 | I878: -0.07097
A879: 46020 | B879: 0.200315 | C879: -1.436149 | D879: -1.1534585 | E879: 0.333496 | F879: 0.85231425 | G879: 0.949697 | H879: 0.28851047 | I879: -0.047358
A880: 46021 | B880: -0.013623 | C880: -0.046927 | D880: 1.1433646 | E880: 0.077362 | F880: -0.31790668 | G880: -0.007351 | H880: -0.80513995 | I880: -0.009461
A881: 46022 | B881: 0 | C881: 0 | E881: 0 | G881: 0 | I881: 0
A882: 46024 | B882: 0.074769 | C882: -0.917519 | D882: -1.7999274 | E882: 0.491883 | F882: 0.88462052 | G882: 0.340085 | H882: 0.9052346 | I882: 0.010781
A883: 46027 | B883: 0.231663 | C883: -0.212355 | D883: 0.97913439 | E883: -0.019271 | F883: -1.23311 | G883: 0.036068 | H883: 0.26417446 | I883: -0.036104
A884: 46028 | B884: -0.174853 | C884: 0.457125 | D884: 3.8090216 | E884: 0.135079 | F884: -0.5810085 | G884: -0.386653 | H884: -3.23142 | I884: -0.030697
A885: 46029 | B885: -1.131585 | C885: 1.24228 | D885: -2.7830764 | E885: 0.424889 | F885: 1.5608487 | G885: -0.391166 | H885: 1.2287102 | I885: -0.144419
A886: 46030 | B886: -0.087582 | C886: 0.180076 | D886: 1.168738 | E886: 0.120889 | F886: -0.85185607 | G886: 0.137256 | H886: -0.33647295 | I886: -0.350639
A887: 46031 | B887: -1.953182 | C887: 0.624192 | D887: 1.2968834 | E887: -0.294692 | F887: 0.046132652 | G887: 1.607154 | H887: -1.3128167 | I887: 0.016528
A888: 46034 | B888: -0.491889 | C888: 0.648659 | D888: -0.0545959 | E888: 0.140436 | F888: -0.046298468 | G888: -0.460804 | H888: 0.071746601 | I888: 0.163597
A889: 46035 | B889: -0.32007 | C889: 0.960314 | D889: -1.9628502 | E889: 0.411765 | F889: 0.52024325 | G889: -1.32039 | H889: 1.4156614 | I889: 0.268382
A890: 46036 | B890: -0.545247 | C890: 1.646056 | D890: 3.0076368 | E890: -0.50192 | F890: -2.1347982 | G890: -0.606271 | H890: -0.56752088 | I890: 0.007382
A891: 46037 | B891: 0.545681 | C891: 0.585082 | D891: -0.3533331 | E891: -0.061381 | F891: 0.2377632 | G891: -1.124504 | H891: 0.10282502 | I891: 0.055123
A892: 46038 | B892: -0.47762 | C892: 2.115416 | D892: -1.1298871 | E892: -0.425044 | F892: 0.91474809 | G892: -1.214529 | H892: 0.24161605 | I892: 0.001776
A893: 46041 | B893: -0.251952 | C893: 0.314356 | D893: 0.16971208 | E893: 0.282818 | F893: -0.21366946 | G893: -0.156015 | H893: 0.060598187 | I893: -0.189207
... A1012: 46216 | B1012: 0.154849 | C1012: -0.1775 | D1012: -2.7019977 | E1012: 0.370647 | F1012: 2.0415227 | G1012: -0.324882 | H1012: 0.58683293 | I1012: -0.023113
A1013: 46217 | D1013: -0.2028678 | F1013: -0.46258136 | H1013: 0.74763268

Sheet raw_monthly
A1: date | B1: financial_cash | C1: foreign_cash | D1: foreign_primary_cash | E1: foreign_futures | F1: individual_cash | G1: individual_futures | H1: institutional_cash | I1: institutional_futures | J1: others_cash
A2: 44773 | B2: 0 | C2: 0 | D2: 0 | E2: -0.5427065 | F2: 0 | G2: -1.1257466 | H2: 0 | I2: 1.990734 | J2: 0
A3: 44804 | B3: 0 | C3: 0 | D3: 0 | E3: -5.8493498 | F3: 0 | G3: 0.27425304 | H3: 0 | I3: 5.373032 | J3: 0
A4: 44834 | B4: 0 | C4: 0 | D4: 0 | E4: -3.4807675 | F4: 0 | G4: -0.31468657 | H4: 0 | I4: 3.9940674 | J4: 0
A5: 44865 | B5: 0 | C5: 0 | D5: 0 | E5: -4.3675584 | F5: 0 | G5: 0.19520984 | H5: 0 | I5: 3.904765 | J5: 0
A6: 44895 | B6: 0 | C6: 0 | D6: 0 | E6: 5.1756744 | F6: 0 | G6: 0.46149456 | H6: 0 | I6: -4.4786141 | J6: 0
A7: 44926 | B7: 0 | C7: 0 | D7: 0 | E7: -3.9206751 | F7: 0 | G7: 0.23940262 | H7: 0 | I7: 4.0239144 | J7: 0
A8: 44957 | B8: 0 | C8: 0 | D8: 0 | E8: 6.4038982 | F8: 0 | G8: -0.11583512 | H8: 0 | I8: -5.8292095 | J8: 0
A9: 44985 | B9: 0 | C9: 0 | D9: 0 | E9: -9.8103643 | F9: 0 | G9: 1.5605374 | H9: 0 | I9: 8.1062897 | J9: 0
A10: 45016 | B10: 0 | C10: 0 | D10: 0 | E10: -2.4092593 | F10: 0 | G10: -0.12054005 | H10: 0 | I10: 2.9882903 | J10: 0
A11: 45046 | B11: 0.15199 | C11: -0.686824 | D11: 0 | E11: 3.3148152 | F11: 1.338074 | G11: -0.48174122 | H11: -1.08758 | I11: -3.3005078 | J11: 0.28434
A12: 45077 | B12: -0.05642 | C12: -4.279477 | D12: 0 | E12: -6.0369512 | F12: -1.015181 | G12: 0.23317679 | H12: 2.034563 | I12: 5.8068652 | J12: 3.316517
A13: 45107 | B13: -1.782354 | C13: 10.139883 | D13: 0 | E13: -9.6848068 | F13: -1.094558 | G13: -0.44809476 | H13: -9.628888 | I13: 9.099226 | J13: 2.365917
... A50: 46234 | B50: 0.705205 | C50: 1.130505 | D50: 0 | E50: 0.78841007 | F50: 0.519823 | G50: -0.47423866 | H50: -2.843548 | I50: -0.22871379 | J50: 0.488016
B53: =SUM(B49,C49,F49,H49,J49) -> 9.4368957e-16

Sheet raw_participation
A1: date | B1: individuals | C1: institutions | D1: foreign | E1: financial_institutions | F1: others
A2: 42369 | B2: 0.137 | C2: 0.2719 | D2: 0.5279 | E2: 0.0512 | F2: 0.0119
A3: 42735 | B3: 0.170039 | C3: 0.248684 | D3: 0.522758 | E3: 0.052257 | F3: 0.010569
A4: 43100 | B4: 0.168082 | C4: 0.272115 | D4: 0.484297 | E4: 0.059575 | F4: 0.014951
A5: 43465 | B5: 0.1786 | C5: 0.2781 | D5: 0.489 | E5: 0.0456 | F5: 0.0086
A6: 43496 | B6: 0.187 | C6: 0.297 | D6: 0.4635 | E6: 0.0431 | F6: 0.0094
A7: 43524 | B7: 0.177 | C7: 0.3047 | D7: 0.4591 | E7: 0.0508 | F7: 0.0083
A8: 43555 | B8: 0.1831 | C8: 0.3029 | D8: 0.4601 | E8: 0.049 | F8: 0.0049
A9: 43585 | B9: 0.182 | C9: 0.2961 | D9: 0.4666 | E9: 0.0495 | F9: 0.0058
A10: 43616 | B10: 0.1763 | C10: 0.2941 | D10: 0.4736 | E10: 0.0499 | F10: 0.0061
A11: 43646 | B11: 0.1761 | C11: 0.3139 | D11: 0.4497 | E11: 0.0499 | F11: 0.0104
A12: 43677 | B12: 0.2004 | C12: 0.3137 | D12: 0.4366 | E12: 0.0427 | F12: 0.0066
A13: 43708 | B13: 0.1746 | C13: 0.3218 | D13: 0.4499 | E13: 0.047 | F13: 0.0066
... A96: 46234 | B96: 0.128 | C96: 0.237 | D96: 0.6 | E96: 0.027 | F96: 0.009

Sheet Cap  Líq  por Classe (Anual)
A1: Ano | B1: Renda Fixa | C1: Ações | D1: Multimercados | E1: Previdência | F1: ETF
A2: 44562 | B2: -57169.531 | C2: 2326.0574 | D2: -164514.75 | E2: 0 | F2: 0
A3: 44927 | B3: -58042.07 | C3: 3323.5287 | D3: -180911.58 | E3: 0 | F3: 0
A4: 45292 | B4: 259715.03 | C4: -15782.37 | D4: -349364.85 | E4: 38309.7 | F4: -852.2
A5: 45658 | B5: 84168.909 | C5: -49288.433 | D5: -46048.598 | E5: -19625.613 | F5: 22864.385
A6: 46023 | B6: 108445.83 | C6: -6541.8694 | D6: -9877.7518 | E6: -8582.9087 | F6: 32482.425

Sheet B3 Flows

Sheet Foreign
A1: =TODAY()-35 -> 46183 | D1: =EOMONTH(TODAY(),-12) -> 45869
L2: =MATCH(L3,foreign_annual[#Headers],0) -> 1 | M2: =MATCH(M3,foreign_annual[#Headers],0) -> 2 | N2: =MATCH(N3,foreign_annual[#Headers],0) -> 3 | O2: =MATCH(O3,foreign_annual[#Headers],0) -> 4 | P2: =MATCH(P3,foreign_annual[#Headers],0) -> 5 | Q2: =MATCH(Q3,foreign_annual[#Headers],0) -> 6
D3: =MATCH(D4,monthly_b3[#Headers],0) -> 1 | E3: =MATCH(E4,monthly_b3[#Headers],0) -> 3 | F3: =MATCH(F4,monthly_b3[#Headers],0) -> 5 | G3: =MATCH(G4,monthly_b3[#Headers],0) -> 4 | L3: year | M3: foreign_secondary_cash | N3: foreign_primary_cash | O3: foreign_cash_consolidated | P3: foreign_futures | Q3: foreign_total_cash_plus_futures
D4: date | E4: foreign_cash | F4: foreign_futures | G4: foreign_primary_cash | H4: Total Cash | I4: Total | L4: {=_xlfn.CHOOSECOLS(foreign_annual[],Foreign!L2,Foreign!M2,Foreign!N2,Foreign!O2,Foreign!P2,Foreign!Q2)} -> 2008 | M4: -24.6297 | N4: 16.0655 | O4: -8.5642 | P4: 0 | Q4: 0
D5: {=_xlfn._xlws.FILTER(_xlfn.CHOOSECOLS(monthly_b3[],Foreign!D3,Foreign!E3,Foreign!F3,G3),monthly_b3[date]>=Foreign!$D$1)} -> 45869 | E5: -6.371969 | F5: -7.3110221 | G5: 0.1042 | H5: =E5+G5 -> -6.267769 | I5: =SUM(E5,F5) -> -13.682991 | L5: 2009 | M5: 20.5966 | N5: 30.066 | O5: 50.6626 | P5: 0 | Q5: 0
D6: 45900 | E6: 1.16831 | F6: -6.2264527 | G6: 0 | H6: =E6+G6 -> 1.16831 | I6: =SUM(E6,F6) -> -5.0581427 | L6: 2010 | M6: 5.958 | N6: 40.4714 | O6: 46.4294 | P6: 0 | Q6: 0
D7: 45930 | E7: 5.267106 | F7: 5.1958857 | G7: 0 | H7: =E7+G7 -> 5.267106 | I7: =SUM(E7,F7) -> 10.462992 | L7: 2011 | M7: -1.3519 | N7: 9.8813 | O7: 8.5294 | P7: 0 | Q7: 0
D8: 45961 | E8: -1.22645 | F8: 3.1841459 | G8: 0.0945 | H8: =E8+G8 -> -1.13195 | I8: =SUM(E8,F8) -> 1.9576959 | L8: 2012 | M8: 1.8222 | N8: 4.8275 | O8: 6.6497 | P8: 0 | Q8: 0
D9: 45991 | E9: 2.06082 | F9: -6.8242586 | G9: 0.4893 | H9: =E9+G9 -> 2.55012 | I9: =SUM(E9,F9) -> -4.7634386 | L9: 2013 | M9: 11.7463 | N9: 9.9314 | O9: 21.6777 | P9: 0 | Q9: 0
D10: 46022 | E10: -1.873479 | F10: 6.5027097 | G10: 0.2533 | H10: =E10+G10 -> -1.620179 | I10: =SUM(E10,F10) -> 4.6292307 | L10: 2014 | M10: 20.3426 | N10: 5.5208 | O10: 25.8634 | P10: 0 | Q10: 0
D11: 46053 | E11: 26.313596 | F11: 1.3343747 | G11: 0.1577 | H11: =E11+G11 -> 26.471296 | I11: =SUM(E11,F11) -> 27.647971 | L11: 2015 | M11: 16.387079 | N11: 11.984092 | O11: 28.371171 | P11: 0 | Q11: 0
D12: 46081 | E12: 15.395726 | F12: -10.564151 | G12: 0 | H12: =E12+G12 -> 15.395726 | I12: =SUM(E12,F12) -> 4.8315746 | L12: 2016 | M12: 14.3254 | N12: 5.2161 | O12: 19.5415 | P12: 0 | Q12: 0
D13: 46112 | E13: 11.655508 | F13: -7.1123866 | G13: 0.3088 | H13: =E13+G13 -> 11.964308 | I13: =SUM(E13,F13) -> 4.5431214 | L13: 2017 | M13: 14.354 | N13: 25.2008 | O13: 39.5548 | P13: 0 | Q13: 0
D14: 46142 | E14: 3.178723 | F14: -3.6454207 | G14: 0.0429 | H14: =E14+G14 -> 3.221623 | I14: =SUM(E14,F14) -> -0.46669765 | L14: 2018 | M14: -11.5211 | N14: 6.6896 | O14: -4.8315 | P14: 0.576832 | Q14: -4.254668
D15: 46173 | E15: -14.91 | F15: 1.7111798 | G15: 1.6351 | H15: =E15+G15 -> -13.2749 | I15: =SUM(E15,F15) -> -13.19882 | L15: 2019 | M15: -44.5174 | N15: 38.019 | O15: -6.4984 | P15: -4.194369 | Q15: -10.692769
D16: 46203 | E16: -7.785573 | F16: 0.077054913 | G16: 0.7383 | H16: =E16+G16 -> -7.047273 | I16: =SUM(E16,F16) -> -7.7085181 | L16: 2020 | M16: -39.6635 | N16: 40.3646 | O16: 0.7012 | P16: 2.617767 | Q16: 3.318967
D17: 46234 | E17: 1.130505 | F17: 0.78841007 | G17: 0 | H17: =E17+G17 -> 1.130505 | I17: =SUM(E17,F17) -> 1.9189151 | L17: 2021 | M17: -7.1524 | N17: 48.6904 | O17: 41.538 | P17: 27.192255 | Q17: 68.730255
L18: 2022 | M18: 100.8243 | N18: 18.9702 | O18: 119.7943 | P18: -1.863147 | Q18: 117.93115
L19: 2023 | M19: 44.8534 | N19: 11.1016 | O19: 55.9545 | P19: 2.464804 | Q19: 58.419304
L20: 2024 | M20: -32.1083 | N20: 7.9099 | O20: -24.1982 | P20: 5.26925 | Q20: -18.92895
L21: 2025 | M21: 25.473 | N21: 1.3972 | O21: 26.8704 | P21: -7.873738 | Q21: 18.996662
L22: 2026 | M22: 34.978485 | N22: 2.8828 | O22: 37.861285 | P22: -17.410939 | Q22: 20.450346

Sheet Institutional
A1: =TODAY()-35 -> 46183 | H1: =EOMONTH(TODAY(),-12) -> 45869
B3: =MATCH(B4,daily_b3[#Headers],0) -> 1 | C3: =MATCH(C4,daily_b3[#Headers],0) -> 7 | D3: =MATCH(D4,daily_b3[#Headers],0) -> 8 | H3: =MATCH(H4,monthly_b3[#Headers],0) -> 1 | I3: =MATCH(I4,monthly_b3[#Headers],0) -> 8 | J3: =MATCH(J4,monthly_b3[#Headers],0) -> 9
B4: date | C4: institutional_cash | D4: institutional_futures | E4: Total | H4: date | I4: institutional_cash | J4: institutional_futures | K4: Total
B5: {=_xlfn._xlws.FILTER(_xlfn.CHOOSECOLS(daily_b3[],Institutional!B3,Institutional!C3,Institutional!D3),daily_b3[date]>=Institutional!A1)} -> 46183 | C5: 0.544805 | D5: -0.028449975 | E5: =SUM(C5,D5) -> 0.51635502 | H5: {=_xlfn._xlws.FILTER(_xlfn.CHOOSECOLS(monthly_b3[],Institutional!H3,Institutional!I3,Institutional!J3),monthly_b3[date]>=Institutional!$H$1)} -> 45869 | I5: -0.519521 | J5: 4.2185808 | K5: =SUM(I5,J5) -> 3.6990598
B6: 46184 | C6: 0.466251 | D6: 2.1969711 | E6: =SUM(C6,D6) -> 2.6632221 | H6: 45900 | I6: -1.280379 | J6: 9.2737978 | K6: =SUM(I6,J6) -> 7.9934188
B7: 46185 | C7: -0.636768 | D7: -0.39147118 | E7: =SUM(C7,D7) -> -1.0282392 | H7: 45930 | I7: -9.2146 | J7: -6.1161535 | K7: =SUM(I7,J7) -> -15.330754
B8: 46188 | C8: -0.673957 | D8: 0.22605635 | E8: =SUM(C8,D8) -> -0.44790065 | H8: 45961 | I8: 0.285306 | J8: -1.6809325 | K8: =SUM(I8,J8) -> -1.3956265
B9: 46189 | C9: 1.220733 | D9: -2.8325357 | E9: =SUM(C9,D9) -> -1.6118027 | H9: 45991 | I9: -8.741159 | J9: 5.1488821 | K9: =SUM(I9,J9) -> -3.5922769
B10: 46190 | C10: -0.171993 | D10: -1.8119871 | E10: =SUM(C10,D10) -> -1.9839801 | H10: 46022 | I10: 2.891489 | J10: -8.5009125 | K10: =SUM(I10,J10) -> -5.6094235
B11: 46191 | C11: -0.372111 | D11: 0.41955585 | E11: =SUM(C11,D11) -> 0.047444847 | H11: 46053 | I11: -17.538169 | J11: -0.36041536 | K11: =SUM(I11,J11) -> -17.898584
B12: 46192 | C12: -2.732827 | D12: -0.30568443 | E12: =SUM(C12,D12) -> -3.0385114 | H12: 46081 | I12: -12.788471 | J12: 9.4720787 | K12: =SUM(I12,J12) -> -3.3163923
B13: 46195 | C13: 1.520575 | D13: 0.50372534 | E13: =SUM(C13,D13) -> 2.0243003 | H13: 46112 | I13: -9.949229 | J13: 8.1753807 | K13: =SUM(I13,J13) -> -1.7738483
B14: 46196 | C14: 0.786346 | D14: -0.091896317 | E14: =SUM(C14,D14) -> 0.69444968 | H14: 46142 | I14: -9.444606 | J14: 2.0480833 | K14: =SUM(I14,J14) -> -7.3965227
B15: 46197 | C15: 0.339694 | D15: 1.9262056 | E15: =SUM(C15,D15) -> 2.2658996 | H15: 46173 | I15: 13.329085 | J15: -3.1966362 | K15: =SUM(I15,J15) -> 10.132449
B16: 46198 | C16: 0.23721 | D16: 0.90508801 | E16: =SUM(C16,D16) -> 1.142298 | H16: 46203 | I16: 1.788724 | J16: 0.76300511 | K16: =SUM(I16,J16) -> 2.5517291
B17: 46199 | C17: 0.408311 | D17: 1.5682706 | E17: =SUM(C17,D17) -> 1.9765816 | H17: 46234 | I17: -2.843548 | J17: -0.22871379 | K17: =SUM(I17,J17) -> -3.0722618
B18: 46202 | C18: -0.766988 | D18: 0.095796447 | E18: =SUM(C18,D18) -> -0.67119155
B19: 46203 | C19: -0.850967 | D19: -0.55468568 | E19: =SUM(C19,D19) -> -1.4056527
B20: 46204 | C20: 0.199038 | D20: -1.6826573 | E20: =SUM(C20,D20) -> -1.4836193
B21: 46205 | C21: -0.119224 | D21: 0.32175965 | E21: =SUM(C21,D21) -> 0.20253565
B22: 46206 | C22: -0.679627 | D22: 0.15511443 | E22: =SUM(C22,D22) -> -0.52451257
B23: 46209 | C23: -0.391866 | D23: 2.1493327 | E23: =SUM(C23,D23) -> 1.7574667
B24: 46210 | C24: -0.5771 | D24: -0.92616626 | E24: =SUM(C24,D24) -> -1.5032663
B25: 46211 | C25: 0.17241 | D25: -1.515294 | E25: =SUM(C25,D25) -> -1.342884
B26: 46212 | C26: -0.281495 | D26: -0.14543022 | E26: =SUM(C26,D26) -> -0.42692522 | I26: =I16+PFs!I16 -> 4.94413 | J26: =J16+PFs!J16 -> 0.20750727
B27: 46213 | C27: -0.840802 | D27: 0.080161608 | E27: =SUM(C27,D27) -> -0.76064039
B28: 46216 | C28: -0.324882 | D28: 0.58683293
B29: 46217 | C29: 0 | D29: 0.74763268

Sheet PFs
A1: =TODAY()-35 -> 46183 | H1: =EOMONTH(TODAY(),-12) -> 45869
B3: =MATCH(B4,daily_b3[#Headers],0) -> 1 | C3: =MATCH(C4,daily_b3[#Headers],0) -> 5 | D3: =MATCH(D4,daily_b3[#Headers],0) -> 6 | H3: =MATCH(H4,monthly_b3[#Headers],0) -> 1 | I3: =MATCH(I4,monthly_b3[#Headers],0) -> 6 | J3: =MATCH(J4,monthly_b3[#Headers],0) -> 7
B4: date | C4: individual_cash | D4: individual_futures | E4: Total | H4: date | I4: individual_cash | J4: individual_futures | K4: Total
B5: {=_xlfn._xlws.FILTER(_xlfn.CHOOSECOLS(daily_b3[],PFs!B3,PFs!C3,PFs!D3),daily_b3[date]>=PFs!A1)} -> 46183 | C5: 0.29809 | D5: 0.14813123 | E5: =SUM(C5,D5) -> 0.44622123 | H5: {=_xlfn._xlws.FILTER(_xlfn.CHOOSECOLS(monthly_b3[],PFs!H3,PFs!I3,PFs!J3),monthly_b3[date]>=PFs!$H$1)} -> 45869 | I5: 1.052135 | J5: 2.4338461 | K5: =SUM(I5,J5) -> 3.4859811
B6: 46184 | C6: -0.104276 | D6: -0.90869017 | E6: =SUM(C6,D6) -> -1.0129662 | H6: 45900 | I6: -1.361087 | J6: -3.0614057 | K6: =SUM(I6,J6) -> -4.4224927
B7: 46185 | C7: 0.256918 | D7: 0.42110503 | E7: =SUM(C7,D7) -> 0.67802303 | H7: 45930 | I7: -0.118863 | J7: 1.3290396 | K7: =SUM(I7,J7) -> 1.2101766
B8: 46188 | C8: -0.508268 | D8: 0.62058062 | E8: =SUM(C8,D8) -> 0.11231262 | H8: 45961 | I8: 0.758163 | J8: -1.0948306 | K8: =SUM(I8,J8) -> -0.33666762
B9: 46189 | C9: 0.362564 | D9: -0.094101762 | E9: =SUM(C9,D9) -> 0.26846224 | H9: 45991 | I9: -3.486114 | J9: 0.50334231 | K9: =SUM(I9,J9) -> -2.9827717
B10: 46190 | C10: 0.254027 | D10: -0.37865262 | E10: =SUM(C10,D10) -> -0.12462562 | H10: 46022 | I10: 3.861349 | J10: 2.4881468 | K10: =SUM(I10,J10) -> 6.3494958
B11: 46191 | C11: 0.076979 | D11: -0.2985503 | E11: =SUM(C11,D11) -> -0.2215713 | H11: 46053 | I11: -3.571473 | J11: -0.91350014 | K11: =SUM(I11,J11) -> -4.4849731
B12: 46192 | C12: 0.556468 | D12: -0.13268142 | E12: =SUM(C12,D12) -> 0.42378658 | H12: 46081 | I12: -2.734582 | J12: 1.3775954 | K12: =SUM(I12,J12) -> -1.3569866
B13: 46195 | C13: 0.019238 | D13: -0.29660362 | E13: =SUM(C13,D13) -> -0.27736562 | H13: 46112 | I13: 0.276786 | J13: -0.9770744 | K13: =SUM(I13,J13) -> -0.7002884
B14: 46196 | C14: 0.138116 | D14: -0.1900782 | E14: =SUM(C14,D14) -> -0.051962199 | H14: 46142 | I14: 0.03299 | J14: 1.8815836 | K14: =SUM(I14,J14) -> 1.9145736
B15: 46197 | C15: 0.26237 | D15: 0.20753535 | E15: =SUM(C15,D15) -> 0.46990535 | H15: 46173 | I15: 5.820614 | J15: 1.531599 | K15: =SUM(I15,J15) -> 7.352213
B16: 46198 | C16: -0.069962 | D16: 0.17460564 | E16: =SUM(C16,D16) -> 0.10464364 | H16: 46203 | I16: 3.155406 | J16: -0.55549785 | K16: =SUM(I16,J16) -> 2.5999082
B17: 46199 | C17: -0.099316 | D17: -0.64834431 | E17: =SUM(C17,D17) -> -0.74766031 | H17: 46234 | I17: 0.519823 | J17: -0.47423866 | K17: =SUM(I17,J17) -> 0.045584344
B18: 46202 | C18: 0.008004 | D18: 0.60882383 | E18: =SUM(C18,D18) -> 0.61682783
B19: 46203 | C19: 0.319288 | D19: 0.34090274 | E19: =SUM(C19,D19) -> 0.66019074 | H19: =I16+Institutional!I16 -> 4.94413 | I19: =J16+Institutional!J16 -> 0.20750727
B20: 46204 | C20: 0.186669 | D20: -0.32987718 | E20: =SUM(C20,D20) -> -0.14320818
B21: 46205 | C21: 0.076914 | D21: 0.000660824 | E21: =SUM(C21,D21) -> 0.077574824
B22: 46206 | C22: -0.213172 | D22: -0.48464658 | E22: =SUM(C22,D22) -> -0.69781858
B23: 46209 | C23: 0.464662 | D23: 1.0699726 | E23: =SUM(C23,D23) -> 1.5346346
B24: 46210 | C24: 0.302524 | D24: 0.026895985 | E24: =SUM(C24,D24) -> 0.32941999
B25: 46211 | C25: 0.220425 | D25: -0.090826357 | E25: =SUM(C25,D25) -> 0.12959864
B26: 46212 | C26: -0.247875 | D26: -1.4228212 | E26: =SUM(C26,D26) -> -1.6706962 | I26: =I16+Foreign!E16+Institutional!I16+'Fin Inst.'!F16+Others!F16 -> 1.1657342e-15
B27: 46213 | C27: -0.640971 | D27: -0.82253808 | E27: =SUM(C27,D27) -> -1.4635091
B28: 46216 | C28: 0.370647 | D28: 2.0415227 | E28: =SUM(C28,D28) -> 2.4121697
B29: 46217 | C29: 0 | D29: -0.46258136

Sheet Fin Inst.
A1: =TODAY()-35 -> 46183 | E1: =EOMONTH(TODAY(),-12) -> 45869
B3: =MATCH(B4,daily_b3[#Headers],0) -> 1 | C3: =MATCH(C4,daily_b3[#Headers],0) -> 2 | E3: =MATCH(E4,monthly_b3[#Headers],0) -> 1 | F3: =MATCH(F4,monthly_b3[#Headers],0) -> 2
B4: date | C4: financial_cash | E4: date | F4: financial_cash
B5: {=_xlfn._xlws.FILTER(_xlfn.CHOOSECOLS(daily_b3[],'Fin Inst.'!B3,'Fin Inst.'!C3),daily_b3[date]>='Fin Inst.'!A1)} -> 46183 | C5: -0.298675 | E5: {=_xlfn._xlws.FILTER(_xlfn.CHOOSECOLS(monthly_b3[],'Fin Inst.'!E3,'Fin Inst.'!F3),monthly_b3[date]>='Fin Inst.'!$E$1)} -> 45869 | F5: 5.346434
B6: 46184 | C6: 0.486304 | E6: 45900 | F6: 1.032225
B7: 46185 | C7: 0.365606 | E7: 45930 | F7: -1.686363
B8: 46188 | C8: 0.044736 | E8: 45961 | F8: -0.379364
B9: 46189 | C9: -0.679334 | E9: 45991 | F9: 3.363629
B10: 46190 | C10: -0.319556 | E10: 46022 | F10: -2.556037
B11: 46191 | C11: -0.037059 | E11: 46053 | F11: -4.686354
B12: 46192 | C12: 2.000924 | E12: 46081 | F12: 1.649246
B13: 46195 | C13: 0.457543 | E13: 46112 | F13: -4.767923
B14: 46196 | C14: 0.023936 | E14: 46142 | F14: 4.987639
B15: 46197 | C15: 0.14308 | E15: 46173 | F15: -1.52885
B16: 46198 | C16: 0.221088 | E16: 46203 | F16: 2.368177
B17: 46199 | C17: -0.339656 | E17: 46234 | F17: 0.705205
B18: 46202 | C18: 0.053263
B19: 46203 | C19: 0.164012
B20: 46204 | C20: 0.119975
B21: 46205 | C21: -0.60261
B22: 46206 | C22: 0.204765
B23: 46209 | C23: 0.325304
B24: 46210 | C24: 0.177853
B25: 46211 | C25: 0.067006
B26: 46212 | C26: 0.28684
B27: 46213 | C27: -0.028777
B28: 46216 | C28: 0.154849
B29: 46217 | C29: 0

Sheet Others
A1: =TODAY()-35 -> 46183 | E1: =EOMONTH(TODAY(),-12) -> 45869
B3: =MATCH(B4,daily_b3[#Headers],0) -> 1 | C3: =MATCH(C4,daily_b3[#Headers],0) -> 9 | E3: =MATCH(E4,monthly_b3[#Headers],0) -> 1 | F3: =MATCH(F4,monthly_b3[#Headers],0) -> 10
B4: date | C4: others_cash | E4: date | F4: others_cash
B5: {=_xlfn._xlws.FILTER(_xlfn.CHOOSECOLS(daily_b3[],Others!B3,Others!C3),daily_b3[date]>=Others!A1)} -> 46183 | C5: -0.395174 | E5: {=_xlfn._xlws.FILTER(_xlfn.CHOOSECOLS(monthly_b3[],Others!E3,Others!F3),monthly_b3[date]>=Others!$E$1)} -> 45869 | F5: 0.492922
B6: 46184 | C6: -0.097192 | E6: 45900 | F6: 0.440931
B7: 46185 | C7: 0.016523 | E7: 45930 | F7: 5.752722
B8: 46188 | C8: 0.139205 | E8: 45961 | F8: 0.562344
B9: 46189 | C9: 0.300083 | E9: 45991 | F9: 6.802824
B10: 46190 | C10: 0.164762 | E10: 46022 | F10: -2.323321
B11: 46191 | C11: 0.251421 | E11: 46053 | F11: -0.517601
B12: 46192 | C12: 0.177152 | E12: 46081 | F12: -1.521919
B13: 46195 | C13: 0.088861 | E13: 46112 | F13: 2.784858
B14: 46196 | C14: 0.114936 | E14: 46142 | F14: 1.245254
B15: 46197 | C15: 0.110373 | E15: 46173 | F15: -2.710849
B16: 46198 | C16: 0.022446 | E16: 46203 | F16: 0.473266
B17: 46199 | C17: -0.004078 | E17: 46234 | F17: 0.488016
B18: 46202 | C18: 0.039203
B19: 46203 | C19: 0.065579
B20: 46204 | C20: 0.084143
B21: 46205 | C21: 0.077318
B22: 46206 | C22: -0.010105
B23: 46209 | C23: 0.102218
B24: 46210 | C24: 0.084541
B25: 46211 | C25: 0.147778
B26: 46212 | C26: 0.036159
B27: 46213 | C27: -0.010923
B28: 46216 | C28: -0.023113
B29: 46217 | C29: 0

Sheet Participação B3
A1: 43496
C3: Individuals | D3: Institutions | E3: Foreign | F3: Financial Inst. | G3: Others
B4: {=_xlfn._xlws.FILTER(participation[#All],participation[[#All],[date]]>='Participação B3'!A1)} -> date | C4: individuals | D4: institutions | E4: foreign | F4: financial_institutions | G4: others | K4: Individuals | L4: Institutions | M4: Foreign | N4: Financial Inst. | O4: Others
B5: 43496 | C5: 0.187 | D5: 0.297 | E5: 0.4635 | F5: 0.0431 | G5: 0.0094 | K5: Pessoas físicas | L5: Instituições | M5: Estrangeiro | N5: Inst.Financ. | O5: Outros
B6: 43524 | C6: 0.177 | D6: 0.3047 | E6: 0.4591 | F6: 0.0508 | G6: 0.0083 | J6: =MAX(B5:B1048576) -> 46234 | K6: =INDEX(C:C,MATCH($J6,$B:$B,0)) -> 0.128 | L6: =INDEX(D:D,MATCH($J6,$B:$B,0)) -> 0.237 | M6: =INDEX(E:E,MATCH($J6,$B:$B,0)) -> 0.6 | N6: =INDEX(F:F,MATCH($J6,$B:$B,0)) -> 0.027 | O6: =INDEX(G:G,MATCH($J6,$B:$B,0)) -> 0.009
B7: 43555 | C7: 0.1831 | D7: 0.3029 | E7: 0.4601 | F7: 0.049 | G7: 0.0049
B8: 43585 | C8: 0.182 | D8: 0.2961 | E8: 0.4666 | F8: 0.0495 | G8: 0.0058
B9: 43616 | C9: 0.1763 | D9: 0.2941 | E9: 0.4736 | F9: 0.0499 | G9: 0.0061
B10: 43646 | C10: 0.1761 | D10: 0.3139 | E10: 0.4497 | F10: 0.0499 | G10: 0.0104
B11: 43677 | C11: 0.2004 | D11: 0.3137 | E11: 0.4366 | F11: 0.0427 | G11: 0.0066
B12: 43708 | C12: 0.1746 | D12: 0.3218 | E12: 0.4499 | F12: 0.047 | G12: 0.0066
B13: 43738 | C13: 0.1826 | D13: 0.3104 | E13: 0.4625 | F13: 0.0388 | G13: 0.0056
B14: 43769 | C14: 0.1838 | D14: 0.3237 | E14: 0.4414 | F14: 0.045 | G14: 0.0061
B15: 43799 | C15: 0.1883 | D15: 0.3322 | E15: 0.4332 | F15: 0.0388 | G15: 0.0075
B16: 43830 | C16: 0.1713 | D16: 0.3518 | E16: 0.4258 | F16: 0.0448 | G16: 0.0063
B17: 43861 | C17: 0.1937 | D17: 0.3314 | E17: 0.4228 | F17: 0.044 | G17: 0.0081
B18: 43890 | C18: 0.1593 | D18: 0.3387 | E18: 0.4508 | F18: 0.0437 | G18: 0.0075
... B95: 46234 | C95: 0.128 | D95: 0.237 | E95: 0.6 | F95: 0.027 | G95: 0.009

Sheet Sector flows
E2: YTD | G2: =EOMONTH(TODAY(),-1) -> 46203 | I2: MTD
C3: =MATCH('Sector flows'!C4,Sheet1__2[#Headers],0) -> 2 | D3: =MATCH('Sector flows'!D4,Sheet1__2[#Headers],0) -> 4 | E3: =MATCH('Sector flows'!E4,Sheet1__2[#Headers],0) -> 5 | F3: =MATCH('Sector flows'!F4,Sheet1__2[#Headers],0) -> 12 | G3: =MATCH('Sector flows'!G4,Sheet1__2[#Headers],0) -> 13 | H3: =MATCH('Sector flows'!H4,Sheet1__2[#Headers],0) -> 20 | I3: =MATCH('Sector flows'!I4,Sheet1__2[#Headers],0) -> 21
C4: sector | D4: ytd_foreigners_flow | E4: ytd_foreigners_flow_to_63d_adtv | F4: last_month_foreigners_flow | G4: last_month_foreigners_flow_to_63d_adtv | H4: mtd_foreigners_flow | I4: mtd_foreigners_flow_to_63d_adtv
C5: {=_xlfn._xlws.SORT(_xlfn.CHOOSECOLS(Sheet1__2[#Data],'Sector flows'!C3,'Sector flows'!D3,'Sector flows'!E3,'Sector flows'!F3,'Sector flows'!G3,'Sector flows'!H3,'Sector flows'!I3),7)} -> Food & Beverages | D5: -2.6955304e+09 | E5: -4.9283391 | F5: -1.1466082e+09 | G5: -2.0963866 | H5: -4.5539266e+08 | I5: -0.83261144
C6: Metals & Mining | D6: 9.2707969e+09 | E6: 4.5759446 | F6: -1.8661949e+08 | G6: -0.092112949 | H6: -1.3950397e+09 | I6: -0.68857344
C7: Agribusiness | D7: -3.9071934e+08 | E7: -3.6557071 | F7: -2.6927775e+08 | G7: -2.519457 | H7: -55075801 | I7: -0.5153085
C8: Homebuilders | D8: -1.6963768e+09 | E8: -2.8747469 | F8: -72353666 | G8: -0.12261337 | H8: -1.7491598e+08 | I8: -0.29641951
C9: TMT | D9: -2.0295577e+09 | E9: -4.0185914 | F9: -4.716435e+08 | G9: -0.93386973 | H9: -1.0771145e+08 | I9: -0.21327223
C10: Oil, Gas & Petrochemicals | D10: 2.8928533e+10 | E10: 7.7954357 | F10: 8.9538469e+08 | G10: 0.24128129 | H10: -4.5241208e+08 | I10: -0.12191248
C11: Capital Goods | D11: -5.3946111e+08 | E11: -0.69503236 | F11: -1.6572953e+08 | G11: -0.21352306 | H11: 4018617.8 | I11: 0.0051775177
C12: Income Properties | D12: -30748093 | E12: -0.091040687 | F12: -1.2254796e+08 | G12: -0.36284691 | H12: 12184273 | I12: 0.036075881
C13: Education | D13: -5.3664284e+08 | E13: -3.9818479 | F13: -54076631 | G13: -0.40124438 | H13: 8373347.6 | I13: 0.062129585
C14: Transportation | D14: -1.9692794e+09 | E14: -2.2832633 | F14: -4.0016152e+08 | G14: -0.46396367 | H14: 56524371 | I14: 0.065536674
C15: Financials Non-Banks | D15: 3.497645e+09 | E15: 2.6669174 | F15: -1.1598501e+09 | G15: -0.88437347 | H15: 2.4019422e+08 | I15: 0.18314556
C16: Utilities & Energy | D16: 6.3446986e+09 | E16: 3.1799168 | F16: 1.8187377e+08 | G16: 0.091153809 | H16: 5.6717889e+08 | I16: 0.28426594
C17: Pulp & Paper | D17: 1.3825635e+08 | E17: 0.40325106 | F17: -73966722 | G17: -0.21573808 | H17: 1.093423e+08 | I17: 0.3189177
... C21: Sanitation | D21: 2.3867535e+09 | E21: 3.0613087 | F21: 9.3541116e+08 | G21: 1.1997814 | H21: 5.5446811e+08 | I21: 0.71117443
G25: 46021 | H25: {=MAX(_xlfn._xlws.FILTER(Sheet1__3[data],MONTH(Sheet1__3[data])<>MONTH(EOMONTH(TODAY(),-1))))} -> 46213
D26: Accumulated Foreign Flows to 63d ADTV | G26: =MAX(Sheet1__3[data]) -> 46213 | H26: =MAX(Sheet1__3[data]) -> 46213
C27: Sector | D27: YTD | E27: =G2 -> 46203 | F27: MTD | G27: YTD Performance | H27: MTD Performance
C28: {=_xlfn._xlws.SORT(_xlfn.CHOOSECOLS(C5:I21,1,3,5,7),4,-1)} -> Sanitation | D28: 3.0613087 | E28: 1.1997814 | F28: 0.71117443 | G28: =INDEX(Sheet1__3[#All],MATCH('Sector flows'!$G$26,Sheet1__3[data],0),MATCH('Sector flows'!$C28,Sheet1__3[#Headers],0))/INDEX(Sheet1__3[#All],MATCH('Sector flows'!$G$25,Sheet1__3[data],0),MATCH('Sector flows'!$C28,Sheet1__3[#Headers],0))-1 -> 0.1829835 | H28: =INDEX(Sheet1__3[#All],MATCH('Sector flows'!$H$26,Sheet1__3[data],0),MATCH('Sector flows'!$C28,Sheet1__3[#Headers],0))/INDEX(Sheet1__3[#All],MATCH('Sector flows'!$H$25,Sheet1__3[data],0),MATCH('Sector flows'!$C28,Sheet1__3[#Headers],0))-1 -> 0
C29: Banks | D29: 0.57795467 | E29: -0.95640433 | F29: 0.62261995 | G29: =INDEX(Sheet1__3[#All],MATCH('Sector flows'!$G$26,Sheet1__3[data],0),MATCH('Sector flows'!$C29,Sheet1__3[#Headers],0))/INDEX(Sheet1__3[#All],MATCH('Sector flows'!$G$25,Sheet1__3[data],0),MATCH('Sector flows'!$C29,Sheet1__3[#Headers],0))-1 -> 0.05780904 | H29: =INDEX(Sheet1__3[#All],MATCH('Sector flows'!$H$26,Sheet1__3[data],0),MATCH('Sector flows'!$C29,Sheet1__3[#Headers],0))/INDEX(Sheet1__3[#All],MATCH('Sector flows'!$H$25,Sheet1__3[data],0),MATCH('Sector flows'!$C29,Sheet1__3[#Headers],0))-1 -> 0
C30: Health Care | D30: -8.0211673 | E30: -0.12885098 | F30: 0.37755043 | G30: =INDEX(Sheet1__3[#All],MATCH('Sector flows'!$G$26,Sheet1__3[data],0),MATCH('Sector flows'!$C30,Sheet1__3[#Headers],0))/INDEX(Sheet1__3[#All],MATCH('Sector flows'!$G$25,Sheet1__3[data],0),MATCH('Sector flows'!$C30,Sheet1__3[#Headers],0))-1 -> -0.11510144 | H30: =INDEX(Sheet1__3[#All],MATCH('Sector flows'!$H$26,Sheet1__3[data],0),MATCH('Sector flows'!$C30,Sheet1__3[#Headers],0))/INDEX(Sheet1__3[#All],MATCH('Sector flows'!$H$25,Sheet1__3[data],0),MATCH('Sector flows'!$C30,Sheet1__3[#Headers],0))-1 -> 0
C31: Retail | D31: -1.2955123 | E31: -0.87409069 | F31: 0.33948392 | G31: =INDEX(Sheet1__3[#All],MATCH('Sector flows'!$G$26,Sheet1__3[data],0),MATCH('Sector flows'!$C31,Sheet1__3[#Headers],0))/INDEX(Sheet1__3[#All],MATCH('Sector flows'!$G$25,Sheet1__3[data],0),MATCH('Sector flows'!$C31,Sheet1__3[#Headers],0))-1 -> -0.10010248 | H31: =INDEX(Sheet1__3[#All],MATCH('Sector flows'!$H$26,Sheet1__3[data],0),MATCH('Sector flows'!$C31,Sheet1__3[#Headers],0))/INDEX(Sheet1__3[#All],MATCH('Sector flows'!$H$25,Sheet1__3[data],0),MATCH('Sector flows'!$C31,Sheet1__3[#Headers],0))-1 -> 0
C32: Pulp & Paper | D32: 0.40325106 | E32: -0.21573808 | F32: 0.3189177 | G32: =INDEX(Sheet1__3[#All],MATCH('Sector flows'!$G$26,Sheet1__3[data],0),MATCH('Sector flows'!$C32,Sheet1__3[#Headers],0))/INDEX(Sheet1__3[#All],MATCH('Sector flows'!$G$25,Sheet1__3[data],0),MATCH('Sector flows'!$C32,Sheet1__3[#Headers],0))-1 -> -0.1617222 | H32: =INDEX(Sheet1__3[#All],MATCH('Sector flows'!$H$26,Sheet1__3[data],0),MATCH('Sector flows'!$C32,Sheet1__3[#Headers],0))/INDEX(Sheet1__3[#All],MATCH('Sector flows'!$H$25,Sheet1__3[data],0),MATCH('Sector flows'!$C32,Sheet1__3[#Headers],0))-1 -> 0
C33: Utilities & Energy | D33: 3.1799168 | E33: 0.091153809 | F33: 0.28426594 | G33: =INDEX(Sheet1__3[#All],MATCH('Sector flows'!$G$26,Sheet1__3[data],0),MATCH('Sector flows'!$C33,Sheet1__3[#Headers],0))/INDEX(Sheet1__3[#All],MATCH('Sector flows'!$G$25,Sheet1__3[data],0),MATCH('Sector flows'!$C33,Sheet1__3[#Headers],0))-1 -> 0.09613619 | H33: =INDEX(Sheet1__3[#All],MATCH('Sector flows'!$H$26,Sheet1__3[data],0),MATCH('Sector flows'!$C33,Sheet1__3[#Headers],0))/INDEX(Sheet1__3[#All],MATCH('Sector flows'!$H$25,Sheet1__3[data],0),MATCH('Sector flows'!$C33,Sheet1__3[#Headers],0))-1 -> 0
C34: Financials Non-Banks | D34: 2.6669174 | E34: -0.88437347 | F34: 0.18314556 | G34: =INDEX(Sheet1__3[#All],MATCH('Sector flows'!$G$26,Sheet1__3[data],0),MATCH('Sector flows'!$C34,Sheet1__3[#Headers],0))/INDEX(Sheet1__3[#All],MATCH('Sector flows'!$G$25,Sheet1__3[data],0),MATCH('Sector flows'!$C34,Sheet1__3[#Headers],0))-1 -> 0.16876805 | H34: =INDEX(Sheet1__3[#All],MATCH('Sector flows'!$H$26,Sheet1__3[data],0),MATCH('Sector flows'!$C34,Sheet1__3[#Headers],0))/INDEX(Sheet1__3[#All],MATCH('Sector flows'!$H$25,Sheet1__3[data],0),MATCH('Sector flows'!$C34,Sheet1__3[#Headers],0))-1 -> 0
C35: Transportation | D35: -2.2832633 | E35: -0.46396367 | F35: 0.065536674 | G35: =INDEX(Sheet1__3[#All],MATCH('Sector flows'!$G$26,Sheet1__3[data],0),MATCH('Sector flows'!$C35,Sheet1__3[#Headers],0))/INDEX(Sheet1__3[#All],MATCH('Sector flows'!$G$25,Sheet1__3[data],0),MATCH('Sector flows'!$C35,Sheet1__3[#Headers],0))-1 -> -0.053397176 | H35: =INDEX(Sheet1__3[#All],MATCH('Sector flows'!$H$26,Sheet1__3[data],0),MATCH('Sector flows'!$C35,Sheet1__3[#Headers],0))/INDEX(Sheet1__3[#All],MATCH('Sector flows'!$H$25,Sheet1__3[data],0),MATCH('Sector flows'!$C35,Sheet1__3[#Headers],0))-1 -> 0
C36: Education | D36: -3.9818479 | E36: -0.40124438 | F36: 0.062129585 | G36: =INDEX(Sheet1__3[#All],MATCH('Sector flows'!$G$26,Sheet1__3[data],0),MATCH('Sector flows'!$C36,Sheet1__3[#Headers],0))/INDEX(Sheet1__3[#All],MATCH('Sector flows'!$G$25,Sheet1__3[data],0),MATCH('Sector flows'!$C36,Sheet1__3[#Headers],0))-1 -> -0.27519882 | H36: =INDEX(Sheet1__3[#All],MATCH('Sector flows'!$H$26,Sheet1__3[data],0),MATCH('Sector flows'!$C36,Sheet1__3[#Headers],0))/INDEX(Sheet1__3[#All],MATCH('Sector flows'!$H$25,Sheet1__3[data],0),MATCH('Sector flows'!$C36,Sheet1__3[#Headers],0))-1 -> 0
C37: Income Properties | D37: -0.091040687 | E37: -0.36284691 | F37: 0.036075881 | G37: =INDEX(Sheet1__3[#All],MATCH('Sector flows'!$G$26,Sheet1__3[data],0),MATCH('Sector flows'!$C37,Sheet1__3[#Headers],0))/INDEX(Sheet1__3[#All],MATCH('Sector flows'!$G$25,Sheet1__3[data],0),MATCH('Sector flows'!$C37,Sheet1__3[#Headers],0))-1 -> 0.057473291 | H37: =INDEX(Sheet1__3[#All],MATCH('Sector flows'!$H$26,Sheet1__3[data],0),MATCH('Sector flows'!$C37,Sheet1__3[#Headers],0))/INDEX(Sheet1__3[#All],MATCH('Sector flows'!$H$25,Sheet1__3[data],0),MATCH('Sector flows'!$C37,Sheet1__3[#Headers],0))-1 -> 0
C38: Capital Goods | D38: -0.69503236 | E38: -0.21352306 | F38: 0.0051775177 | G38: =INDEX(Sheet1__3[#All],MATCH('Sector flows'!$G$26,Sheet1__3[data],0),MATCH('Sector flows'!$C38,Sheet1__3[#Headers],0))/INDEX(Sheet1__3[#All],MATCH('Sector flows'!$G$25,Sheet1__3[data],0),MATCH('Sector flows'!$C38,Sheet1__3[#Headers],0))-1 -> -0.057884381 | H38: =INDEX(Sheet1__3[#All],MATCH('Sector flows'!$H$26,Sheet1__3[data],0),MATCH('Sector flows'!$C38,Sheet1__3[#Headers],0))/INDEX(Sheet1__3[#All],MATCH('Sector flows'!$H$25,Sheet1__3[data],0),MATCH('Sector flows'!$C38,Sheet1__3[#Headers],0))-1 -> 0
C39: Oil, Gas & Petrochemicals | D39: 7.7954357 | E39: 0.24128129 | F39: -0.12191248 | G39: =INDEX(Sheet1__3[#All],MATCH('Sector flows'!$G$26,Sheet1__3[data],0),MATCH('Sector flows'!$C39,Sheet1__3[#Headers],0))/INDEX(Sheet1__3[#All],MATCH('Sector flows'!$G$25,Sheet1__3[data],0),MATCH('Sector flows'!$C39,Sheet1__3[#Headers],0))-1 -> 0.32319473 | H39: =INDEX(Sheet1__3[#All],MATCH('Sector flows'!$H$26,Sheet1__3[data],0),MATCH('Sector flows'!$C39,Sheet1__3[#Headers],0))/INDEX(Sheet1__3[#All],MATCH('Sector flows'!$H$25,Sheet1__3[data],0),MATCH('Sector flows'!$C39,Sheet1__3[#Headers],0))-1 -> 0
C40: TMT | D40: -4.0185914 | E40: -0.93386973 | F40: -0.21327223 | G40: =INDEX(Sheet1__3[#All],MATCH('Sector flows'!$G$26,Sheet1__3[data],0),MATCH('Sector flows'!$C40,Sheet1__3[#Headers],0))/INDEX(Sheet1__3[#All],MATCH('Sector flows'!$G$25,Sheet1__3[data],0),MATCH('Sector flows'!$C40,Sheet1__3[#Headers],0))-1 -> -0.051388851 | H40: =INDEX(Sheet1__3[#All],MATCH('Sector flows'!$H$26,Sheet1__3[data],0),MATCH('Sector flows'!$C40,Sheet1__3[#Headers],0))/INDEX(Sheet1__3[#All],MATCH('Sector flows'!$H$25,Sheet1__3[data],0),MATCH('Sector flows'!$C40,Sheet1__3[#Headers],0))-1 -> 0
... C44: Food & Beverages | D44: -4.9283391 | E44: -2.0963866 | F44: -0.83261144 | G44: =INDEX(Sheet1__3[#All],MATCH('Sector flows'!$G$26,Sheet1__3[data],0),MATCH('Sector flows'!$C44,Sheet1__3[#Headers],0))/INDEX(Sheet1__3[#All],MATCH('Sector flows'!$G$25,Sheet1__3[data],0),MATCH('Sector flows'!$C44,Sheet1__3[#Headers],0))-1 -> 0.047993678 | H44: =INDEX(Sheet1__3[#All],MATCH('Sector flows'!$H$26,Sheet1__3[data],0),MATCH('Sector flows'!$C44,Sheet1__3[#Headers],0))/INDEX(Sheet1__3[#All],MATCH('Sector flows'!$H$25,Sheet1__3[data],0),MATCH('Sector flows'!$C44,Sheet1__3[#Headers],0))-1 -> 0

Sheet Anbima

Sheet Fundos - Classe
B1: AUM | D1: Fundos de renda fixa | E1: Fundos de ações | F1: Fundos multimercado
C2: =MATCH(C3,PL_por_Classe__12M[#Headers],0) -> 1 | D2: =MATCH(D3,PL_por_Classe__12M[#Headers],0) -> 5 | E2: =MATCH(E3,PL_por_Classe__12M[#Headers],0) -> 6 | F2: =MATCH(F3,PL_por_Classe__12M[#Headers],0) -> 7 | Y2: Raio-XP
C3: Período | D3: Renda Fixa (tri) | E3: Ações (tri) | F3: Multimercado (tri)
C4: {=_xlfn.CHOOSECOLS(PL_por_Classe__12M[],C2,D2,E2,F2)} -> 45839 | D4: 4.3002607 | E4: 0.61533144 | F4: 1.6163696
C5: 45870 | D5: 4.3466409 | E5: 0.64523167 | F5: 1.6237815
C6: 45901 | D6: 4.4380191 | E6: 0.66012811 | F6: 1.647632
C7: 45931 | D7: 4.4852325 | E7: 0.66315715 | F7: 1.654037
C8: 45962 | D8: 4.5277812 | E8: 0.68966478 | F8: 1.6679949
C9: 45992 | D9: 4.5055077 | E9: 0.69242821 | F9: 1.6890837
C10: 46023 | D10: 4.6186877 | E10: 0.73267496 | F10: 1.6513457
C11: 46054 | D11: 4.714041 | E11: 0.73849394 | F11: 1.5976017
C12: 46082 | D12: 4.8179219 | E12: 0.72361565 | F12: 1.6045872
C13: 46113 | D13: 4.7928739 | E13: 0.73300278 | F13: 1.6009266
C14: 46143 | D14: 4.7347944 | E14: 0.68979461 | F14: 1.5633007
C15: 46174 | D15: 4.7423032 | E15: 0.68150323 | F15: 1.544815
B19: Flows monthly | D19: Fixed income funds | E19: Equity funds | F19: Hedge funds | L19: Net flow of fixed income funds (R$ billion)
C20: =MATCH(C21,Cap__Líq__por_Classe__12M[#Headers],0) -> 1 | D20: =MATCH(D21,Cap__Líq__por_Classe__12M[#Headers],0) -> 7 | E20: =MATCH(E21,Cap__Líq__por_Classe__12M[#Headers],0) -> 8 | F20: =MATCH(F21,Cap__Líq__por_Classe__12M[#Headers],0) -> 9
C21: Período | D21: Renda Fixa (bi) | E21: Ações (bi) | F21: Multimercado (bi)
C22: {=_xlfn.CHOOSECOLS(Cap__Líq__por_Classe__12M[],C20,D20,E20,F20)} -> 45839 | D22: 14.261665 | E22: -5.1570561 | F22: 6.1291964
C23: 45870 | D23: -7.458452 | E23: 0.48578244 | F23: 5.5145503
C24: 45901 | D24: 50.071232 | E24: -3.6657283 | F24: -3.5827615
C25: 45931 | D25: 12.828317 | E25: -1.3170536 | F25: -3.080097
C26: 45962 | D26: -4.4404167 | E26: 0.43760403 | F26: 7.3912105
C27: 45992 | D27: -67.627253 | E27: 1.6888386 | F27: 7.0939046
C28: 46023 | D28: 59.516226 | E28: -1.2774033 | F28: 20.187893
C29: 46054 | D29: 56.25344 | E29: -3.6351199 | F29: -6.2494841
C30: 46082 | D30: 13.575535 | E30: -0.79544281 | F30: -3.2300136
C31: 46113 | D31: -16.649929 | E31: -0.15962027 | F31: -2.6000296
C32: 46143 | D32: -3.5643098 | E32: -0.69537602 | F32: -3.7083797
C33: 46174 | D33: -0.68512905 | E33: 0.021092855 | F33: -14.277738
L38: Net flow of equity funds (R$ billion)
B39: Flows annual
C41: Período | D41: Renda Fixa (bi) | E41: Ações (bi) | F41: Multimercado (bi)
C42: 2021 | D42: 241 | E42: 5.6 | F42: 59.9
C43: 2022 | D43: -44.7 | E43: -28.1 | F43: -86.3
C44: 2023 | D44: -58 | E44: 3.6 | F44: -181.3
C45: 2024 | D45: 258 | E45: -15.6 | F45: -349.5
C46: 2025 | D46: 84.3 | E46: -54.5 | F46: -58.9
C47: 2026 | D47: ='Cap Líq por Classe (Anual)'!B6/1000 -> 108.44583 | E47: ='Cap Líq por Classe (Anual)'!C6/1000 -> -6.5418694 | F47: ='Cap Líq por Classe (Anual)'!D6/1000 -> -9.8777518
L57: Net flow of hedge funds (R$ billion)

Sheet Fundos de ações
B2: =MATCH(B4,Cap__Líq__Ações_Grupo__12M___2[#Headers],0) -> 1 | C2: =MATCH(C4,Cap__Líq__Ações_Grupo__12M___2[#Headers],0) -> 6 | D2: =MATCH(D4,Cap__Líq__Ações_Grupo__12M___2[#Headers],0) -> 7 | E2: =MATCH(E4,Cap__Líq__Ações_Grupo__12M___2[#Headers],0) -> 8 | F2: =MATCH(F4,Cap__Líq__Ações_Grupo__12M___2[#Headers],0) -> 9
C3: Total | D3: Active funds | E3: International equity funds | F3: Others
B4: Data | C4: Ações (total) (R$ billion) | D4: Fundos ativos (R$ billion) | E4: Fundos de investimento estrangeiro (R$ billion) | F4: Outros (R$ billion)
B5: {=_xlfn.CHOOSECOLS(Cap__Líq__Ações_Grupo__12M___2[],'Fundos de ações'!B2,'Fundos de ações'!C2,'Fundos de ações'!D2,'Fundos de ações'!E2,'Fundos de ações'!F2)} -> 45839 | C5: -5.1570561 | D5: -5.3796571 | E5: 0.93710661 | F5: -0.71450564
B6: 45870 | C6: 0.48578244 | D6: -1.1796197 | E6: 2.1808358 | F6: -0.51543372
B7: 45901 | C7: -3.6657283 | D7: 2.1897243 | E7: -4.831667 | F7: -1.0237856
B8: 45931 | C8: -1.3170536 | D8: -1.3559338 | E8: 0.38626637 | F8: -0.34738616
B9: 45962 | C9: 0.43760403 | D9: -3.6306815 | E9: 4.4261103 | F9: -0.35782483
B10: 45992 | C10: 1.6888386 | D10: 0.17237735 | E10: 1.7402188 | F10: -0.22375752
B11: 46023 | C11: -1.2774033 | D11: -2.4607756 | E11: 1.5970172 | F11: -0.41364484
B12: 46054 | C12: -3.6351199 | D12: -4.7783765 | E12: 6.4929419 | F12: -5.3496853
B13: 46082 | C13: -0.79544281 | D13: -2.2333152 | E13: 3.4673461 | F13: -2.0294738
B14: 46113 | C14: -0.15962027 | D14: 0.67047381 | E14: -0.35541539 | F14: -0.47467869
B15: 46143 | C15: -0.69537602 | D15: -0.59800498 | E15: 0.23366546 | F15: -0.3310365
B16: 46174 | C16: 0.021092855 | D16: -1.6435967 | E16: 0.40902921 | F16: 1.2556604
D17: =SUM(D11:D16) -> -11.043595 | E17: =SUM(E11:E16) -> 11.844584
B23: =MATCH(B25,Aloc__Ações_por_Grupo__Anual[#Headers],0) -> 1 | C23: =MATCH(C25,Aloc__Ações_por_Grupo__Anual[#Headers],0) -> 2 | D23: =MATCH(D25,Aloc__Ações_por_Grupo__Anual[#Headers],0) -> 3 | E23: =MATCH(E25,Aloc__Ações_por_Grupo__Anual[#Headers],0) -> 4 | F23: =MATCH(F25,Aloc__Ações_por_Grupo__Anual[#Headers],0) -> 5
C24: Active funds | D24: International equity funds | E24: Others
B25: Date | C25: Fundos ativos | D25: Fundos de investimento estrangeiro | E25: Outros | F25: Total Ações (R\$ mi)
B26: {=_xlfn.CHOOSECOLS(Aloc__Ações_por_Grupo__Anual[],'Fundos de ações'!B23,'Fundos de ações'!C23,'Fundos de ações'!D23,'Fundos de ações'!E23,'Fundos de ações'!F23)} -> 42705 | C26: 0.52761634 | D26: 0.086138654 | E26: 0.38624501 | F26: 150274.76
B27: 43070 | C27: 0.5019665 | D27: 0.22704975 | E27: 0.27098375 | F27: 228067.13
B28: 43435 | C28: 0.47960291 | D28: 0.18021116 | E28: 0.34018593 | F28: 301741.53
B29: 43800 | C29: 0.59668185 | D29: 0.17733358 | E29: 0.22598457 | F29: 496516.89
B30: 44166 | C30: 0.62975702 | D30: 0.1706477 | E30: 0.19959528 | F30: 607293.46
B31: 44531 | C31: 0.61505016 | D31: 0.25108328 | E31: 0.13386656 | F31: 583805.98
B32: 44896 | C32: 0.53421214 | D32: 0.23112824 | E32: 0.23465962 | F32: 523586.89
B33: 45261 | C33: 0.48832293 | D33: 0.24822005 | E33: 0.26345702 | F33: 627948.41
B34: 45627 | C34: 0.44009248 | D34: 0.30595388 | E34: 0.25395364 | F34: 578025.46
B35: 45992 | C35: 0.43854371 | D35: 0.3804029 | E35: 0.18105339 | F35: 666360.28
B36: 46174 | C36: 0.42733524 | D36: 0.40454655 | E36: 0.16811821 | F36: 681503.23

Sheet Alocação em fundos
B1: Annual relative allocation to equity funds, hedge funds, fixed income funds and other funds
B2: =MATCH(B4,AUM_Allocation__Annual[#Headers],0) -> 1 | C2: =MATCH(C4,AUM_Allocation__Annual[#Headers],0) -> 2 | D2: =MATCH(D4,AUM_Allocation__Annual[#Headers],0) -> 3 | E2: =MATCH(E4,AUM_Allocation__Annual[#Headers],0) -> 4 | F2: =MATCH(F4,AUM_Allocation__Annual[#Headers],0) -> 5
C3: Fixed Income | D3: Equities | E3: Hedge Funds | F3: Others
B4: Date | C4: Fixed Income as % of Total Net AUM | D4: Equities as % of Total Net AUM (RHS) | E4: Hedge Funds as % of Total Net AUM | F4: Others as % of Total Net AUM
B5: {=_xlfn.CHOOSECOLS('AUM Allocation (Annual)'!A44:H56,B2,C2,D2,E2,F2)} -> 41974 | C5: 0.46374153 | D5: 0.065455785 | E5: 0.19775456 | F5: 0.27304812
B6: 42339 | C6: 0.47039927 | D6: 0.046529885 | E6: 0.19651815 | F6: 0.2865527
B7: 42705 | C7: 0.48081439 | D7: 0.042895233 | E7: 0.19082327 | F7: 0.28546711
B8: 43070 | C8: 0.46227595 | D8: 0.054914467 | E8: 0.20154343 | F8: 0.28126615
B9: 43435 | C9: 0.44100564 | D9: 0.065832484 | E9: 0.20997938 | F9: 0.28318249
B10: 43801 | C10: 0.39255363 | D10: 0.090531297 | E10: 0.21613538 | F10: 0.30077969
B11: 44166 | C11: 0.36143725 | D11: 0.10062327 | E11: 0.23252308 | F11: 0.3054164
B12: 44531 | C12: 0.37113327 | D12: 0.084379728 | E12: 0.22775271 | F12: 0.31673429
B13: 44896 | C13: 0.38112965 | D13: 0.070081828 | E13: 0.21811781 | F13: 0.33067071
B14: 45261 | C14: 0.37421408 | D14: 0.074777828 | E14: 0.19756694 | F14: 0.35344115
B15: 45627 | C15: 0.4011496 | D15: 0.061960112 | E15: 0.16178355 | F15: 0.37510674
B16: 45992 | C16: 0.3999165 | D16: 0.061461103 | E16: 0.14992593 | F16: 0.38869646
B17: 46174 | C17: 0.42773782 | D17: 0.061469015 | E17: 0.13933647 | F17: 0.37145669
D18: =AVERAGE(D8:D17) -> 0.072603114
B20: =MATCH(B21,AUM_Allocation__Annual[#Headers],0) -> 1 | C20: =MATCH(C21,AUM_Allocation__Annual[#Headers],0) -> 9 | D20: =MATCH(D21,AUM_Allocation__Annual[#Headers],0) -> 3 | E20: =MATCH(E21,AUM_Allocation__Annual[#Headers],0) -> 10 | F20: =MATCH(F21,AUM_Allocation__Annual[#Headers],0) -> 11
B21: Date | C21: Total Net AUM (R$ tri) | D21: Equities as % of Total Net AUM (RHS) | E21: Total equities AUM (R$ tri) | F21: Total AUM of funds industry (R$ tri)
B22: {=_xlfn.CHOOSECOLS('AUM Allocation (Annual)'!A35:K56,'Alocação em fundos'!B20,'Alocação em fundos'!C20,'Alocação em fundos'!D20,'Alocação em fundos'!E20,'Alocação em fundos'!F20)} -> 38687 | C22: 23.44216 | D22: 0.079850769 | E22: 0.2121096 | F22: 2.656325
B23: 39052 | C23: 28.272094 | D23: 0.09664851 | E23: 0.31509247 | F23: 3.2601896
B24: 39417 | C24: 32.381097 | D24: 0.14879778 | E24: 0.56214495 | F24: 3.7779122
B25: 39783 | C25: 27.20317 | D25: 0.099995247 | E25: 0.32970967 | F25: 3.2972534
B26: 40148 | C26: 33.420411 | D26: 0.1184126 | E26: 0.49516894 | F26: 4.181725
B27: 40513 | C27: 35.550165 | D27: 0.113269 | E27: 0.50936277 | F27: 4.49693
B28: 40878 | C28: 38.041431 | D28: 0.093097045 | E28: 0.46077904 | F28: 4.9494486
B29: 41244 | C29: 41.120718 | D29: 0.0887365 | E29: 0.47904222 | F29: 5.39848
B30: 41609 | C30: 41.363306 | D30: 0.083363465 | E30: 0.4639733 | F30: 5.5656672
B31: 41974 | C31: 42.35873 | D31: 0.065455785 | E31: 0.38140405 | F31: 5.8268961
B32: 42339 | C32: 41.821127 | D32: 0.046529885 | E32: 0.27275066 | F32: 5.8618382
B33: 42705 | C33: 45.70987 | D33: 0.042895233 | E33: 0.27440801 | F33: 6.3971681
B34: 43070 | C34: 54.838027 | D34: 0.054914467 | E34: 0.41898695 | F34: 7.62981
... B43: 46174 | C43: 69.686214 | D43: 0.061469015 | E43: 0.68150323 | F43: 11.086939
C49: =C17*F43 -> 4.7423032
